{
  "key": "bank-first-1c6c10f8-4e94-4e98-8d59-2ad42bc479b7-509f6afc",
  "bankName": "Bank First",
  "productName": "Complete Home Loan Investment 1 year fixed LVR \u003c80%",
  "productId": "1c6c10f8-4e94-4e98-8d59-2ad42bc479b7",
  "firstDate": "2026-05-03",
  "lastDate": "2026-05-10",
  "variants": [
    {
      "key": "FIXED|PRINCIPAL_AND_INTEREST|INVESTMENT|0.0000|0.8000|P12M",
      "rateType": "FIXED",
      "repaymentType": "PRINCIPAL_AND_INTEREST",
      "loanPurpose": "INVESTMENT",
      "lvrMin": 0,
      "lvrMax": 0.8,
      "fixedTerm": "P12M",
      "points": [
        {
          "date": "2026-05-03",
          "rate": 0.0654,
          "comparisonRate": 0.0617
        },
        {
          "date": "2026-05-10",
          "rate": 0.0679,
          "comparisonRate": 0.062
        }
      ]
    }
  ]
}
