{
  "key": "credit-union-sa-creditunionsa-hl-443f1-io-57876ee2",
  "bankName": "Credit Union SA",
  "productName": "1-Year Fixed Rate Home Loan Interest Only",
  "productId": "CREDITUNIONSA_HL_443F1_IO",
  "firstDate": "2026-05-10",
  "lastDate": "2026-05-15",
  "variants": [
    {
      "key": "FIXED|INTEREST_ONLY|INVESTMENT|0.0000|0.0000|P1Y",
      "rateType": "FIXED",
      "repaymentType": "INTEREST_ONLY",
      "loanPurpose": "INVESTMENT",
      "lvrMin": 0,
      "lvrMax": 0,
      "fixedTerm": "P1Y",
      "points": [
        {
          "date": "2026-05-10",
          "rate": 0.0769,
          "comparisonRate": 0.0734
        },
        {
          "date": "2026-05-14",
          "rate": 0.0794,
          "comparisonRate": 0.0759
        },
        {
          "date": "2026-05-15",
          "rate": 0.0794,
          "comparisonRate": 0.0759
        }
      ]
    },
    {
      "key": "FIXED|INTEREST_ONLY|OWNER_OCCUPIED|0.0000|0.0000|P1Y",
      "rateType": "FIXED",
      "repaymentType": "INTEREST_ONLY",
      "loanPurpose": "OWNER_OCCUPIED",
      "lvrMin": 0,
      "lvrMax": 0,
      "fixedTerm": "P1Y",
      "points": [
        {
          "date": "2026-05-10",
          "rate": 0.0799,
          "comparisonRate": 0.0714
        },
        {
          "date": "2026-05-14",
          "rate": 0.0824,
          "comparisonRate": 0.074
        },
        {
          "date": "2026-05-15",
          "rate": 0.0824,
          "comparisonRate": 0.074
        }
      ]
    }
  ]
}
