{
  "key": "hume-bank-limited-mbsub60fix3oopi-v1-a1131f88",
  "bankName": "HUME BANK LIMITED",
  "productName": "myBlue 3 Year Fix O/Occ P+I (up to 60% LVR)",
  "productId": "MBSUB60Fix3OOPI_V1",
  "firstDate": "2026-05-03",
  "lastDate": "2026-05-07",
  "variants": [
    {
      "key": "FIXED|PRINCIPAL_AND_INTEREST|OWNER_OCCUPIED|0.0000|0.0000|P36M",
      "rateType": "FIXED",
      "repaymentType": "PRINCIPAL_AND_INTEREST",
      "loanPurpose": "OWNER_OCCUPIED",
      "lvrMin": 0,
      "lvrMax": 0,
      "fixedTerm": "P36M",
      "points": [
        {
          "date": "2026-05-03",
          "rate": 0.0624,
          "comparisonRate": 0.0595
        },
        {
          "date": "2026-05-07",
          "rate": 0.0624,
          "comparisonRate": 0.0595
        }
      ]
    }
  ]
}
