{
  "key": "lending-and-bank-accounts-both-associated-with-bsb-number-939-200-amp-es-7461a257",
  "bankName": "Lending and bank accounts, both associated with BSB number 939 200",
  "productName": "AMP Essential Home Loan",
  "productId": "AMP_ESSENTIAL_HL",
  "firstDate": "2026-05-10",
  "lastDate": "2026-05-12",
  "variants": [
    {
      "key": "VARIABLE|PRINCIPAL_AND_INTEREST|INVESTMENT|0.0000|0.5000|",
      "rateType": "VARIABLE",
      "repaymentType": "PRINCIPAL_AND_INTEREST",
      "loanPurpose": "INVESTMENT",
      "lvrMin": 0,
      "lvrMax": 0.5,
      "points": [
        {
          "date": "2026-05-10",
          "rate": 0.0654,
          "comparisonRate": 0.0657
        },
        {
          "date": "2026-05-12",
          "rate": 0.0654,
          "comparisonRate": 0.0657
        }
      ]
    },
    {
      "key": "VARIABLE|PRINCIPAL_AND_INTEREST|INVESTMENT|0.5000|0.6000|",
      "rateType": "VARIABLE",
      "repaymentType": "PRINCIPAL_AND_INTEREST",
      "loanPurpose": "INVESTMENT",
      "lvrMin": 0.5,
      "lvrMax": 0.6,
      "points": [
        {
          "date": "2026-05-10",
          "rate": 0.0654,
          "comparisonRate": 0.0657
        },
        {
          "date": "2026-05-12",
          "rate": 0.0654,
          "comparisonRate": 0.0657
        }
      ]
    },
    {
      "key": "VARIABLE|PRINCIPAL_AND_INTEREST|INVESTMENT|0.6000|0.8000|",
      "rateType": "VARIABLE",
      "repaymentType": "PRINCIPAL_AND_INTEREST",
      "loanPurpose": "INVESTMENT",
      "lvrMin": 0.6,
      "lvrMax": 0.8,
      "points": [
        {
          "date": "2026-05-10",
          "rate": 0.0664,
          "comparisonRate": 0.0667
        },
        {
          "date": "2026-05-12",
          "rate": 0.0664,
          "comparisonRate": 0.0667
        }
      ]
    },
    {
      "key": "VARIABLE|PRINCIPAL_AND_INTEREST|INVESTMENT|0.8000|0.9000|",
      "rateType": "VARIABLE",
      "repaymentType": "PRINCIPAL_AND_INTEREST",
      "loanPurpose": "INVESTMENT",
      "lvrMin": 0.8,
      "lvrMax": 0.9,
      "points": [
        {
          "date": "2026-05-10",
          "rate": 0.0664,
          "comparisonRate": 0.0667
        },
        {
          "date": "2026-05-12",
          "rate": 0.0664,
          "comparisonRate": 0.0667
        }
      ]
    },
    {
      "key": "VARIABLE|PRINCIPAL_AND_INTEREST|INVESTMENT|0.9000|0.9500|",
      "rateType": "VARIABLE",
      "repaymentType": "PRINCIPAL_AND_INTEREST",
      "loanPurpose": "INVESTMENT",
      "lvrMin": 0.9,
      "lvrMax": 0.95,
      "points": [
        {
          "date": "2026-05-10",
          "rate": 0.0724,
          "comparisonRate": 0.0727
        },
        {
          "date": "2026-05-12",
          "rate": 0.0724,
          "comparisonRate": 0.0727
        }
      ]
    },
    {
      "key": "VARIABLE|PRINCIPAL_AND_INTEREST|OWNER_OCCUPIED|0.0000|0.5000|",
      "rateType": "VARIABLE",
      "repaymentType": "PRINCIPAL_AND_INTEREST",
      "loanPurpose": "OWNER_OCCUPIED",
      "lvrMin": 0,
      "lvrMax": 0.5,
      "points": [
        {
          "date": "2026-05-10",
          "rate": 0.0634,
          "comparisonRate": 0.0637
        },
        {
          "date": "2026-05-12",
          "rate": 0.0634,
          "comparisonRate": 0.0637
        }
      ]
    },
    {
      "key": "VARIABLE|PRINCIPAL_AND_INTEREST|OWNER_OCCUPIED|0.5000|0.6000|",
      "rateType": "VARIABLE",
      "repaymentType": "PRINCIPAL_AND_INTEREST",
      "loanPurpose": "OWNER_OCCUPIED",
      "lvrMin": 0.5,
      "lvrMax": 0.6,
      "points": [
        {
          "date": "2026-05-10",
          "rate": 0.0634,
          "comparisonRate": 0.0637
        },
        {
          "date": "2026-05-12",
          "rate": 0.0634,
          "comparisonRate": 0.0637
        }
      ]
    },
    {
      "key": "VARIABLE|PRINCIPAL_AND_INTEREST|OWNER_OCCUPIED|0.6000|0.8000|",
      "rateType": "VARIABLE",
      "repaymentType": "PRINCIPAL_AND_INTEREST",
      "loanPurpose": "OWNER_OCCUPIED",
      "lvrMin": 0.6,
      "lvrMax": 0.8,
      "points": [
        {
          "date": "2026-05-10",
          "rate": 0.0644,
          "comparisonRate": 0.0647
        },
        {
          "date": "2026-05-12",
          "rate": 0.0644,
          "comparisonRate": 0.0647
        }
      ]
    },
    {
      "key": "VARIABLE|PRINCIPAL_AND_INTEREST|OWNER_OCCUPIED|0.8000|0.9000|",
      "rateType": "VARIABLE",
      "repaymentType": "PRINCIPAL_AND_INTEREST",
      "loanPurpose": "OWNER_OCCUPIED",
      "lvrMin": 0.8,
      "lvrMax": 0.9,
      "points": [
        {
          "date": "2026-05-10",
          "rate": 0.0649,
          "comparisonRate": 0.0652
        },
        {
          "date": "2026-05-12",
          "rate": 0.0649,
          "comparisonRate": 0.0652
        }
      ]
    },
    {
      "key": "VARIABLE|PRINCIPAL_AND_INTEREST|OWNER_OCCUPIED|0.9000|0.9500|",
      "rateType": "VARIABLE",
      "repaymentType": "PRINCIPAL_AND_INTEREST",
      "loanPurpose": "OWNER_OCCUPIED",
      "lvrMin": 0.9,
      "lvrMax": 0.95,
      "points": [
        {
          "date": "2026-05-10",
          "rate": 0.0699,
          "comparisonRate": 0.0702
        },
        {
          "date": "2026-05-12",
          "rate": 0.0699,
          "comparisonRate": 0.0702
        }
      ]
    }
  ]
}
