{
  "key": "me-bank-cf2579cd-508e-ee11-be36-000d3a79efd0-5cbcfa37",
  "bankName": "ME Bank",
  "productName": "ME Bank EconoME Home Loan",
  "productId": "cf2579cd-508e-ee11-be36-000d3a79efd0",
  "firstDate": "2026-05-03",
  "lastDate": "2026-05-06",
  "variants": [
    {
      "key": "FIXED|INTEREST_ONLY|INVESTMENT|0.0000|0.6000|P12M",
      "rateType": "FIXED",
      "repaymentType": "INTEREST_ONLY",
      "loanPurpose": "INVESTMENT",
      "lvrMin": 0,
      "lvrMax": 0.6,
      "fixedTerm": "P12M",
      "points": [
        {
          "date": "2026-05-03",
          "rate": 0.0674,
          "comparisonRate": 0.0603
        },
        {
          "date": "2026-05-06",
          "rate": 0.0674,
          "comparisonRate": 0.0603
        }
      ]
    },
    {
      "key": "FIXED|INTEREST_ONLY|INVESTMENT|0.0000|0.6000|P24M",
      "rateType": "FIXED",
      "repaymentType": "INTEREST_ONLY",
      "loanPurpose": "INVESTMENT",
      "lvrMin": 0,
      "lvrMax": 0.6,
      "fixedTerm": "P24M",
      "points": [
        {
          "date": "2026-05-03",
          "rate": 0.0649,
          "comparisonRate": 0.0605
        },
        {
          "date": "2026-05-06",
          "rate": 0.0649,
          "comparisonRate": 0.0605
        }
      ]
    },
    {
      "key": "FIXED|INTEREST_ONLY|INVESTMENT|0.0000|0.6000|P36M",
      "rateType": "FIXED",
      "repaymentType": "INTEREST_ONLY",
      "loanPurpose": "INVESTMENT",
      "lvrMin": 0,
      "lvrMax": 0.6,
      "fixedTerm": "P36M",
      "points": [
        {
          "date": "2026-05-03",
          "rate": 0.0664,
          "comparisonRate": 0.0614
        },
        {
          "date": "2026-05-06",
          "rate": 0.0664,
          "comparisonRate": 0.0614
        }
      ]
    },
    {
      "key": "FIXED|INTEREST_ONLY|INVESTMENT|0.0000|0.6000|P48M",
      "rateType": "FIXED",
      "repaymentType": "INTEREST_ONLY",
      "loanPurpose": "INVESTMENT",
      "lvrMin": 0,
      "lvrMax": 0.6,
      "fixedTerm": "P48M",
      "points": [
        {
          "date": "2026-05-03",
          "rate": 0.0694,
          "comparisonRate": 0.0631
        },
        {
          "date": "2026-05-06",
          "rate": 0.0694,
          "comparisonRate": 0.0631
        }
      ]
    },
    {
      "key": "FIXED|INTEREST_ONLY|INVESTMENT|0.0000|0.6000|P60M",
      "rateType": "FIXED",
      "repaymentType": "INTEREST_ONLY",
      "loanPurpose": "INVESTMENT",
      "lvrMin": 0,
      "lvrMax": 0.6,
      "fixedTerm": "P60M",
      "points": [
        {
          "date": "2026-05-03",
          "rate": 0.0694,
          "comparisonRate": 0.0638
        },
        {
          "date": "2026-05-06",
          "rate": 0.0694,
          "comparisonRate": 0.0638
        }
      ]
    },
    {
      "key": "FIXED|INTEREST_ONLY|INVESTMENT|0.6001|0.7000|P12M",
      "rateType": "FIXED",
      "repaymentType": "INTEREST_ONLY",
      "loanPurpose": "INVESTMENT",
      "lvrMin": 0.6001,
      "lvrMax": 0.7,
      "fixedTerm": "P12M",
      "points": [
        {
          "date": "2026-05-03",
          "rate": 0.0674,
          "comparisonRate": 0.0603
        },
        {
          "date": "2026-05-06",
          "rate": 0.0674,
          "comparisonRate": 0.0603
        }
      ]
    },
    {
      "key": "FIXED|INTEREST_ONLY|INVESTMENT|0.6001|0.7000|P24M",
      "rateType": "FIXED",
      "repaymentType": "INTEREST_ONLY",
      "loanPurpose": "INVESTMENT",
      "lvrMin": 0.6001,
      "lvrMax": 0.7,
      "fixedTerm": "P24M",
      "points": [
        {
          "date": "2026-05-03",
          "rate": 0.0649,
          "comparisonRate": 0.0605
        },
        {
          "date": "2026-05-06",
          "rate": 0.0649,
          "comparisonRate": 0.0605
        }
      ]
    },
    {
      "key": "FIXED|INTEREST_ONLY|INVESTMENT|0.6001|0.7000|P36M",
      "rateType": "FIXED",
      "repaymentType": "INTEREST_ONLY",
      "loanPurpose": "INVESTMENT",
      "lvrMin": 0.6001,
      "lvrMax": 0.7,
      "fixedTerm": "P36M",
      "points": [
        {
          "date": "2026-05-03",
          "rate": 0.0664,
          "comparisonRate": 0.0614
        },
        {
          "date": "2026-05-06",
          "rate": 0.0664,
          "comparisonRate": 0.0614
        }
      ]
    },
    {
      "key": "FIXED|INTEREST_ONLY|INVESTMENT|0.6001|0.7000|P48M",
      "rateType": "FIXED",
      "repaymentType": "INTEREST_ONLY",
      "loanPurpose": "INVESTMENT",
      "lvrMin": 0.6001,
      "lvrMax": 0.7,
      "fixedTerm": "P48M",
      "points": [
        {
          "date": "2026-05-03",
          "rate": 0.0694,
          "comparisonRate": 0.0631
        },
        {
          "date": "2026-05-06",
          "rate": 0.0694,
          "comparisonRate": 0.0631
        }
      ]
    },
    {
      "key": "FIXED|INTEREST_ONLY|INVESTMENT|0.6001|0.7000|P60M",
      "rateType": "FIXED",
      "repaymentType": "INTEREST_ONLY",
      "loanPurpose": "INVESTMENT",
      "lvrMin": 0.6001,
      "lvrMax": 0.7,
      "fixedTerm": "P60M",
      "points": [
        {
          "date": "2026-05-03",
          "rate": 0.0694,
          "comparisonRate": 0.0638
        },
        {
          "date": "2026-05-06",
          "rate": 0.0694,
          "comparisonRate": 0.0638
        }
      ]
    },
    {
      "key": "FIXED|INTEREST_ONLY|INVESTMENT|0.7001|0.8000|P12M",
      "rateType": "FIXED",
      "repaymentType": "INTEREST_ONLY",
      "loanPurpose": "INVESTMENT",
      "lvrMin": 0.7001,
      "lvrMax": 0.8,
      "fixedTerm": "P12M",
      "points": [
        {
          "date": "2026-05-03",
          "rate": 0.0674,
          "comparisonRate": 0.0608
        },
        {
          "date": "2026-05-06",
          "rate": 0.0674,
          "comparisonRate": 0.0608
        }
      ]
    },
    {
      "key": "FIXED|INTEREST_ONLY|INVESTMENT|0.7001|0.8000|P24M",
      "rateType": "FIXED",
      "repaymentType": "INTEREST_ONLY",
      "loanPurpose": "INVESTMENT",
      "lvrMin": 0.7001,
      "lvrMax": 0.8,
      "fixedTerm": "P24M",
      "points": [
        {
          "date": "2026-05-03",
          "rate": 0.0649,
          "comparisonRate": 0.061
        },
        {
          "date": "2026-05-06",
          "rate": 0.0649,
          "comparisonRate": 0.061
        }
      ]
    },
    {
      "key": "FIXED|INTEREST_ONLY|INVESTMENT|0.7001|0.8000|P36M",
      "rateType": "FIXED",
      "repaymentType": "INTEREST_ONLY",
      "loanPurpose": "INVESTMENT",
      "lvrMin": 0.7001,
      "lvrMax": 0.8,
      "fixedTerm": "P36M",
      "points": [
        {
          "date": "2026-05-03",
          "rate": 0.0664,
          "comparisonRate": 0.0619
        },
        {
          "date": "2026-05-06",
          "rate": 0.0664,
          "comparisonRate": 0.0619
        }
      ]
    },
    {
      "key": "FIXED|INTEREST_ONLY|INVESTMENT|0.7001|0.8000|P48M",
      "rateType": "FIXED",
      "repaymentType": "INTEREST_ONLY",
      "loanPurpose": "INVESTMENT",
      "lvrMin": 0.7001,
      "lvrMax": 0.8,
      "fixedTerm": "P48M",
      "points": [
        {
          "date": "2026-05-03",
          "rate": 0.0694,
          "comparisonRate": 0.0634
        },
        {
          "date": "2026-05-06",
          "rate": 0.0694,
          "comparisonRate": 0.0634
        }
      ]
    },
    {
      "key": "FIXED|INTEREST_ONLY|INVESTMENT|0.7001|0.8000|P60M",
      "rateType": "FIXED",
      "repaymentType": "INTEREST_ONLY",
      "loanPurpose": "INVESTMENT",
      "lvrMin": 0.7001,
      "lvrMax": 0.8,
      "fixedTerm": "P60M",
      "points": [
        {
          "date": "2026-05-03",
          "rate": 0.0694,
          "comparisonRate": 0.0641
        },
        {
          "date": "2026-05-06",
          "rate": 0.0694,
          "comparisonRate": 0.0641
        }
      ]
    },
    {
      "key": "FIXED|INTEREST_ONLY|INVESTMENT|0.8001|0.9000|P12M",
      "rateType": "FIXED",
      "repaymentType": "INTEREST_ONLY",
      "loanPurpose": "INVESTMENT",
      "lvrMin": 0.8001,
      "lvrMax": 0.9,
      "fixedTerm": "P12M",
      "points": [
        {
          "date": "2026-05-03",
          "rate": 0.0694,
          "comparisonRate": 0.0642
        },
        {
          "date": "2026-05-06",
          "rate": 0.0694,
          "comparisonRate": 0.0642
        }
      ]
    },
    {
      "key": "FIXED|INTEREST_ONLY|INVESTMENT|0.8001|0.9000|P24M",
      "rateType": "FIXED",
      "repaymentType": "INTEREST_ONLY",
      "loanPurpose": "INVESTMENT",
      "lvrMin": 0.8001,
      "lvrMax": 0.9,
      "fixedTerm": "P24M",
      "points": [
        {
          "date": "2026-05-03",
          "rate": 0.0669,
          "comparisonRate": 0.0642
        },
        {
          "date": "2026-05-06",
          "rate": 0.0669,
          "comparisonRate": 0.0642
        }
      ]
    },
    {
      "key": "FIXED|INTEREST_ONLY|INVESTMENT|0.8001|0.9000|P36M",
      "rateType": "FIXED",
      "repaymentType": "INTEREST_ONLY",
      "loanPurpose": "INVESTMENT",
      "lvrMin": 0.8001,
      "lvrMax": 0.9,
      "fixedTerm": "P36M",
      "points": [
        {
          "date": "2026-05-03",
          "rate": 0.0674,
          "comparisonRate": 0.0647
        },
        {
          "date": "2026-05-06",
          "rate": 0.0674,
          "comparisonRate": 0.0647
        }
      ]
    },
    {
      "key": "FIXED|INTEREST_ONLY|INVESTMENT|0.8001|0.9000|P48M",
      "rateType": "FIXED",
      "repaymentType": "INTEREST_ONLY",
      "loanPurpose": "INVESTMENT",
      "lvrMin": 0.8001,
      "lvrMax": 0.9,
      "fixedTerm": "P48M",
      "points": [
        {
          "date": "2026-05-03",
          "rate": 0.0704,
          "comparisonRate": 0.0661
        },
        {
          "date": "2026-05-06",
          "rate": 0.0704,
          "comparisonRate": 0.0661
        }
      ]
    },
    {
      "key": "FIXED|INTEREST_ONLY|INVESTMENT|0.8001|0.9000|P60M",
      "rateType": "FIXED",
      "repaymentType": "INTEREST_ONLY",
      "loanPurpose": "INVESTMENT",
      "lvrMin": 0.8001,
      "lvrMax": 0.9,
      "fixedTerm": "P60M",
      "points": [
        {
          "date": "2026-05-03",
          "rate": 0.0704,
          "comparisonRate": 0.0666
        },
        {
          "date": "2026-05-06",
          "rate": 0.0704,
          "comparisonRate": 0.0666
        }
      ]
    },
    {
      "key": "FIXED|INTEREST_ONLY|INVESTMENT|0.9001|0.9500|P12M",
      "rateType": "FIXED",
      "repaymentType": "INTEREST_ONLY",
      "loanPurpose": "INVESTMENT",
      "lvrMin": 0.9001,
      "lvrMax": 0.95,
      "fixedTerm": "P12M",
      "points": [
        {
          "date": "2026-05-03",
          "rate": 0.0774,
          "comparisonRate": 0.0801
        },
        {
          "date": "2026-05-06",
          "rate": 0.0774,
          "comparisonRate": 0.0801
        }
      ]
    },
    {
      "key": "FIXED|INTEREST_ONLY|INVESTMENT|0.9001|0.9500|P24M",
      "rateType": "FIXED",
      "repaymentType": "INTEREST_ONLY",
      "loanPurpose": "INVESTMENT",
      "lvrMin": 0.9001,
      "lvrMax": 0.95,
      "fixedTerm": "P24M",
      "points": [
        {
          "date": "2026-05-03",
          "rate": 0.0734,
          "comparisonRate": 0.079
        },
        {
          "date": "2026-05-06",
          "rate": 0.0734,
          "comparisonRate": 0.079
        }
      ]
    },
    {
      "key": "FIXED|INTEREST_ONLY|INVESTMENT|0.9001|0.9500|P36M",
      "rateType": "FIXED",
      "repaymentType": "INTEREST_ONLY",
      "loanPurpose": "INVESTMENT",
      "lvrMin": 0.9001,
      "lvrMax": 0.95,
      "fixedTerm": "P36M",
      "points": [
        {
          "date": "2026-05-03",
          "rate": 0.0759,
          "comparisonRate": 0.0791
        },
        {
          "date": "2026-05-06",
          "rate": 0.0759,
          "comparisonRate": 0.0791
        }
      ]
    },
    {
      "key": "FIXED|INTEREST_ONLY|INVESTMENT|0.9001|0.9500|P48M",
      "rateType": "FIXED",
      "repaymentType": "INTEREST_ONLY",
      "loanPurpose": "INVESTMENT",
      "lvrMin": 0.9001,
      "lvrMax": 0.95,
      "fixedTerm": "P48M",
      "points": [
        {
          "date": "2026-05-03",
          "rate": 0.0749,
          "comparisonRate": 0.0784
        },
        {
          "date": "2026-05-06",
          "rate": 0.0749,
          "comparisonRate": 0.0784
        }
      ]
    },
    {
      "key": "FIXED|INTEREST_ONLY|INVESTMENT|0.9001|0.9500|P60M",
      "rateType": "FIXED",
      "repaymentType": "INTEREST_ONLY",
      "loanPurpose": "INVESTMENT",
      "lvrMin": 0.9001,
      "lvrMax": 0.95,
      "fixedTerm": "P60M",
      "points": [
        {
          "date": "2026-05-03",
          "rate": 0.0749,
          "comparisonRate": 0.078
        },
        {
          "date": "2026-05-06",
          "rate": 0.0749,
          "comparisonRate": 0.078
        }
      ]
    },
    {
      "key": "FIXED|INTEREST_ONLY|INVESTMENT|0.9501|1.0000|P12M",
      "rateType": "FIXED",
      "repaymentType": "INTEREST_ONLY",
      "loanPurpose": "INVESTMENT",
      "lvrMin": 0.9501,
      "lvrMax": 1,
      "fixedTerm": "P12M",
      "points": [
        {
          "date": "2026-05-03",
          "rate": 0.0774,
          "comparisonRate": 0.0801
        },
        {
          "date": "2026-05-06",
          "rate": 0.0774,
          "comparisonRate": 0.0801
        }
      ]
    },
    {
      "key": "FIXED|INTEREST_ONLY|INVESTMENT|0.9501|1.0000|P24M",
      "rateType": "FIXED",
      "repaymentType": "INTEREST_ONLY",
      "loanPurpose": "INVESTMENT",
      "lvrMin": 0.9501,
      "lvrMax": 1,
      "fixedTerm": "P24M",
      "points": [
        {
          "date": "2026-05-03",
          "rate": 0.0734,
          "comparisonRate": 0.079
        },
        {
          "date": "2026-05-06",
          "rate": 0.0734,
          "comparisonRate": 0.079
        }
      ]
    },
    {
      "key": "FIXED|INTEREST_ONLY|INVESTMENT|0.9501|1.0000|P36M",
      "rateType": "FIXED",
      "repaymentType": "INTEREST_ONLY",
      "loanPurpose": "INVESTMENT",
      "lvrMin": 0.9501,
      "lvrMax": 1,
      "fixedTerm": "P36M",
      "points": [
        {
          "date": "2026-05-03",
          "rate": 0.0759,
          "comparisonRate": 0.0791
        },
        {
          "date": "2026-05-06",
          "rate": 0.0759,
          "comparisonRate": 0.0791
        }
      ]
    },
    {
      "key": "FIXED|INTEREST_ONLY|INVESTMENT|0.9501|1.0000|P48M",
      "rateType": "FIXED",
      "repaymentType": "INTEREST_ONLY",
      "loanPurpose": "INVESTMENT",
      "lvrMin": 0.9501,
      "lvrMax": 1,
      "fixedTerm": "P48M",
      "points": [
        {
          "date": "2026-05-03",
          "rate": 0.0749,
          "comparisonRate": 0.0784
        },
        {
          "date": "2026-05-06",
          "rate": 0.0749,
          "comparisonRate": 0.0784
        }
      ]
    },
    {
      "key": "FIXED|INTEREST_ONLY|INVESTMENT|0.9501|1.0000|P60M",
      "rateType": "FIXED",
      "repaymentType": "INTEREST_ONLY",
      "loanPurpose": "INVESTMENT",
      "lvrMin": 0.9501,
      "lvrMax": 1,
      "fixedTerm": "P60M",
      "points": [
        {
          "date": "2026-05-03",
          "rate": 0.0749,
          "comparisonRate": 0.078
        },
        {
          "date": "2026-05-06",
          "rate": 0.0749,
          "comparisonRate": 0.078
        }
      ]
    },
    {
      "key": "FIXED|INTEREST_ONLY|OWNER_OCCUPIED|0.0000|0.6000|P12M",
      "rateType": "FIXED",
      "repaymentType": "INTEREST_ONLY",
      "loanPurpose": "OWNER_OCCUPIED",
      "lvrMin": 0,
      "lvrMax": 0.6,
      "fixedTerm": "P12M",
      "points": [
        {
          "date": "2026-05-03",
          "rate": 0.0709,
          "comparisonRate": 0.0597
        },
        {
          "date": "2026-05-06",
          "rate": 0.0709,
          "comparisonRate": 0.0597
        }
      ]
    },
    {
      "key": "FIXED|INTEREST_ONLY|OWNER_OCCUPIED|0.0000|0.6000|P24M",
      "rateType": "FIXED",
      "repaymentType": "INTEREST_ONLY",
      "loanPurpose": "OWNER_OCCUPIED",
      "lvrMin": 0,
      "lvrMax": 0.6,
      "fixedTerm": "P24M",
      "points": [
        {
          "date": "2026-05-03",
          "rate": 0.0679,
          "comparisonRate": 0.0603
        },
        {
          "date": "2026-05-06",
          "rate": 0.0679,
          "comparisonRate": 0.0603
        }
      ]
    },
    {
      "key": "FIXED|INTEREST_ONLY|OWNER_OCCUPIED|0.0000|0.6000|P36M",
      "rateType": "FIXED",
      "repaymentType": "INTEREST_ONLY",
      "loanPurpose": "OWNER_OCCUPIED",
      "lvrMin": 0,
      "lvrMax": 0.6,
      "fixedTerm": "P36M",
      "points": [
        {
          "date": "2026-05-03",
          "rate": 0.0659,
          "comparisonRate": 0.0606
        },
        {
          "date": "2026-05-06",
          "rate": 0.0659,
          "comparisonRate": 0.0606
        }
      ]
    },
    {
      "key": "FIXED|INTEREST_ONLY|OWNER_OCCUPIED|0.0000|0.6000|P48M",
      "rateType": "FIXED",
      "repaymentType": "INTEREST_ONLY",
      "loanPurpose": "OWNER_OCCUPIED",
      "lvrMin": 0,
      "lvrMax": 0.6,
      "fixedTerm": "P48M",
      "points": [
        {
          "date": "2026-05-03",
          "rate": 0.0699,
          "comparisonRate": 0.0626
        },
        {
          "date": "2026-05-06",
          "rate": 0.0699,
          "comparisonRate": 0.0626
        }
      ]
    },
    {
      "key": "FIXED|INTEREST_ONLY|OWNER_OCCUPIED|0.0000|0.6000|P60M",
      "rateType": "FIXED",
      "repaymentType": "INTEREST_ONLY",
      "loanPurpose": "OWNER_OCCUPIED",
      "lvrMin": 0,
      "lvrMax": 0.6,
      "fixedTerm": "P60M",
      "points": [
        {
          "date": "2026-05-03",
          "rate": 0.0719,
          "comparisonRate": 0.0643
        },
        {
          "date": "2026-05-06",
          "rate": 0.0719,
          "comparisonRate": 0.0643
        }
      ]
    },
    {
      "key": "FIXED|INTEREST_ONLY|OWNER_OCCUPIED|0.6001|0.7000|P12M",
      "rateType": "FIXED",
      "repaymentType": "INTEREST_ONLY",
      "loanPurpose": "OWNER_OCCUPIED",
      "lvrMin": 0.6001,
      "lvrMax": 0.7,
      "fixedTerm": "P12M",
      "points": [
        {
          "date": "2026-05-03",
          "rate": 0.0709,
          "comparisonRate": 0.0597
        },
        {
          "date": "2026-05-06",
          "rate": 0.0709,
          "comparisonRate": 0.0597
        }
      ]
    },
    {
      "key": "FIXED|INTEREST_ONLY|OWNER_OCCUPIED|0.6001|0.7000|P24M",
      "rateType": "FIXED",
      "repaymentType": "INTEREST_ONLY",
      "loanPurpose": "OWNER_OCCUPIED",
      "lvrMin": 0.6001,
      "lvrMax": 0.7,
      "fixedTerm": "P24M",
      "points": [
        {
          "date": "2026-05-03",
          "rate": 0.0679,
          "comparisonRate": 0.0603
        },
        {
          "date": "2026-05-06",
          "rate": 0.0679,
          "comparisonRate": 0.0603
        }
      ]
    },
    {
      "key": "FIXED|INTEREST_ONLY|OWNER_OCCUPIED|0.6001|0.7000|P36M",
      "rateType": "FIXED",
      "repaymentType": "INTEREST_ONLY",
      "loanPurpose": "OWNER_OCCUPIED",
      "lvrMin": 0.6001,
      "lvrMax": 0.7,
      "fixedTerm": "P36M",
      "points": [
        {
          "date": "2026-05-03",
          "rate": 0.0659,
          "comparisonRate": 0.0606
        },
        {
          "date": "2026-05-06",
          "rate": 0.0659,
          "comparisonRate": 0.0606
        }
      ]
    },
    {
      "key": "FIXED|INTEREST_ONLY|OWNER_OCCUPIED|0.6001|0.7000|P48M",
      "rateType": "FIXED",
      "repaymentType": "INTEREST_ONLY",
      "loanPurpose": "OWNER_OCCUPIED",
      "lvrMin": 0.6001,
      "lvrMax": 0.7,
      "fixedTerm": "P48M",
      "points": [
        {
          "date": "2026-05-03",
          "rate": 0.0699,
          "comparisonRate": 0.0626
        },
        {
          "date": "2026-05-06",
          "rate": 0.0699,
          "comparisonRate": 0.0626
        }
      ]
    },
    {
      "key": "FIXED|INTEREST_ONLY|OWNER_OCCUPIED|0.6001|0.7000|P60M",
      "rateType": "FIXED",
      "repaymentType": "INTEREST_ONLY",
      "loanPurpose": "OWNER_OCCUPIED",
      "lvrMin": 0.6001,
      "lvrMax": 0.7,
      "fixedTerm": "P60M",
      "points": [
        {
          "date": "2026-05-03",
          "rate": 0.0719,
          "comparisonRate": 0.0643
        },
        {
          "date": "2026-05-06",
          "rate": 0.0719,
          "comparisonRate": 0.0643
        }
      ]
    },
    {
      "key": "FIXED|INTEREST_ONLY|OWNER_OCCUPIED|0.7001|0.8000|P12M",
      "rateType": "FIXED",
      "repaymentType": "INTEREST_ONLY",
      "loanPurpose": "OWNER_OCCUPIED",
      "lvrMin": 0.7001,
      "lvrMax": 0.8,
      "fixedTerm": "P12M",
      "points": [
        {
          "date": "2026-05-03",
          "rate": 0.0709,
          "comparisonRate": 0.0602
        },
        {
          "date": "2026-05-06",
          "rate": 0.0709,
          "comparisonRate": 0.0602
        }
      ]
    },
    {
      "key": "FIXED|INTEREST_ONLY|OWNER_OCCUPIED|0.7001|0.8000|P24M",
      "rateType": "FIXED",
      "repaymentType": "INTEREST_ONLY",
      "loanPurpose": "OWNER_OCCUPIED",
      "lvrMin": 0.7001,
      "lvrMax": 0.8,
      "fixedTerm": "P24M",
      "points": [
        {
          "date": "2026-05-03",
          "rate": 0.0679,
          "comparisonRate": 0.0607
        },
        {
          "date": "2026-05-06",
          "rate": 0.0679,
          "comparisonRate": 0.0607
        }
      ]
    },
    {
      "key": "FIXED|INTEREST_ONLY|OWNER_OCCUPIED|0.7001|0.8000|P36M",
      "rateType": "FIXED",
      "repaymentType": "INTEREST_ONLY",
      "loanPurpose": "OWNER_OCCUPIED",
      "lvrMin": 0.7001,
      "lvrMax": 0.8,
      "fixedTerm": "P36M",
      "points": [
        {
          "date": "2026-05-03",
          "rate": 0.0659,
          "comparisonRate": 0.0609
        },
        {
          "date": "2026-05-06",
          "rate": 0.0659,
          "comparisonRate": 0.0609
        }
      ]
    },
    {
      "key": "FIXED|INTEREST_ONLY|OWNER_OCCUPIED|0.7001|0.8000|P48M",
      "rateType": "FIXED",
      "repaymentType": "INTEREST_ONLY",
      "loanPurpose": "OWNER_OCCUPIED",
      "lvrMin": 0.7001,
      "lvrMax": 0.8,
      "fixedTerm": "P48M",
      "points": [
        {
          "date": "2026-05-03",
          "rate": 0.0699,
          "comparisonRate": 0.0629
        },
        {
          "date": "2026-05-06",
          "rate": 0.0699,
          "comparisonRate": 0.0629
        }
      ]
    },
    {
      "key": "FIXED|INTEREST_ONLY|OWNER_OCCUPIED|0.7001|0.8000|P60M",
      "rateType": "FIXED",
      "repaymentType": "INTEREST_ONLY",
      "loanPurpose": "OWNER_OCCUPIED",
      "lvrMin": 0.7001,
      "lvrMax": 0.8,
      "fixedTerm": "P60M",
      "points": [
        {
          "date": "2026-05-03",
          "rate": 0.0719,
          "comparisonRate": 0.0646
        },
        {
          "date": "2026-05-06",
          "rate": 0.0719,
          "comparisonRate": 0.0646
        }
      ]
    },
    {
      "key": "FIXED|INTEREST_ONLY|OWNER_OCCUPIED|0.8001|0.9000|P12M",
      "rateType": "FIXED",
      "repaymentType": "INTEREST_ONLY",
      "loanPurpose": "OWNER_OCCUPIED",
      "lvrMin": 0.8001,
      "lvrMax": 0.9,
      "fixedTerm": "P12M",
      "points": [
        {
          "date": "2026-05-03",
          "rate": 0.0734,
          "comparisonRate": 0.0623
        },
        {
          "date": "2026-05-06",
          "rate": 0.0734,
          "comparisonRate": 0.0623
        }
      ]
    },
    {
      "key": "FIXED|INTEREST_ONLY|OWNER_OCCUPIED|0.8001|0.9000|P24M",
      "rateType": "FIXED",
      "repaymentType": "INTEREST_ONLY",
      "loanPurpose": "OWNER_OCCUPIED",
      "lvrMin": 0.8001,
      "lvrMax": 0.9,
      "fixedTerm": "P24M",
      "points": [
        {
          "date": "2026-05-03",
          "rate": 0.0679,
          "comparisonRate": 0.0624
        },
        {
          "date": "2026-05-06",
          "rate": 0.0679,
          "comparisonRate": 0.0624
        }
      ]
    },
    {
      "key": "FIXED|INTEREST_ONLY|OWNER_OCCUPIED|0.8001|0.9000|P36M",
      "rateType": "FIXED",
      "repaymentType": "INTEREST_ONLY",
      "loanPurpose": "OWNER_OCCUPIED",
      "lvrMin": 0.8001,
      "lvrMax": 0.9,
      "fixedTerm": "P36M",
      "points": [
        {
          "date": "2026-05-03",
          "rate": 0.0649,
          "comparisonRate": 0.0622
        },
        {
          "date": "2026-05-06",
          "rate": 0.0649,
          "comparisonRate": 0.0622
        }
      ]
    },
    {
      "key": "FIXED|INTEREST_ONLY|OWNER_OCCUPIED|0.8001|0.9000|P48M",
      "rateType": "FIXED",
      "repaymentType": "INTEREST_ONLY",
      "loanPurpose": "OWNER_OCCUPIED",
      "lvrMin": 0.8001,
      "lvrMax": 0.9,
      "fixedTerm": "P48M",
      "points": [
        {
          "date": "2026-05-03",
          "rate": 0.0679,
          "comparisonRate": 0.0635
        },
        {
          "date": "2026-05-06",
          "rate": 0.0679,
          "comparisonRate": 0.0635
        }
      ]
    },
    {
      "key": "FIXED|INTEREST_ONLY|OWNER_OCCUPIED|0.8001|0.9000|P60M",
      "rateType": "FIXED",
      "repaymentType": "INTEREST_ONLY",
      "loanPurpose": "OWNER_OCCUPIED",
      "lvrMin": 0.8001,
      "lvrMax": 0.9,
      "fixedTerm": "P60M",
      "points": [
        {
          "date": "2026-05-03",
          "rate": 0.0699,
          "comparisonRate": 0.0649
        },
        {
          "date": "2026-05-06",
          "rate": 0.0699,
          "comparisonRate": 0.0649
        }
      ]
    },
    {
      "key": "FIXED|INTEREST_ONLY|OWNER_OCCUPIED|0.9001|0.9500|P12M",
      "rateType": "FIXED",
      "repaymentType": "INTEREST_ONLY",
      "loanPurpose": "OWNER_OCCUPIED",
      "lvrMin": 0.9001,
      "lvrMax": 0.95,
      "fixedTerm": "P12M",
      "points": [
        {
          "date": "2026-05-03",
          "rate": 0.0744,
          "comparisonRate": 0.0753
        },
        {
          "date": "2026-05-06",
          "rate": 0.0744,
          "comparisonRate": 0.0753
        }
      ]
    },
    {
      "key": "FIXED|INTEREST_ONLY|OWNER_OCCUPIED|0.9001|0.9500|P24M",
      "rateType": "FIXED",
      "repaymentType": "INTEREST_ONLY",
      "loanPurpose": "OWNER_OCCUPIED",
      "lvrMin": 0.9001,
      "lvrMax": 0.95,
      "fixedTerm": "P24M",
      "points": [
        {
          "date": "2026-05-03",
          "rate": 0.0689,
          "comparisonRate": 0.0741
        },
        {
          "date": "2026-05-06",
          "rate": 0.0689,
          "comparisonRate": 0.0741
        }
      ]
    },
    {
      "key": "FIXED|INTEREST_ONLY|OWNER_OCCUPIED|0.9001|0.9500|P36M",
      "rateType": "FIXED",
      "repaymentType": "INTEREST_ONLY",
      "loanPurpose": "OWNER_OCCUPIED",
      "lvrMin": 0.9001,
      "lvrMax": 0.95,
      "fixedTerm": "P36M",
      "points": [
        {
          "date": "2026-05-03",
          "rate": 0.0659,
          "comparisonRate": 0.0727
        },
        {
          "date": "2026-05-06",
          "rate": 0.0659,
          "comparisonRate": 0.0727
        }
      ]
    },
    {
      "key": "FIXED|INTEREST_ONLY|OWNER_OCCUPIED|0.9001|0.9500|P48M",
      "rateType": "FIXED",
      "repaymentType": "INTEREST_ONLY",
      "loanPurpose": "OWNER_OCCUPIED",
      "lvrMin": 0.9001,
      "lvrMax": 0.95,
      "fixedTerm": "P48M",
      "points": [
        {
          "date": "2026-05-03",
          "rate": 0.0689,
          "comparisonRate": 0.073
        },
        {
          "date": "2026-05-06",
          "rate": 0.0689,
          "comparisonRate": 0.073
        }
      ]
    },
    {
      "key": "FIXED|INTEREST_ONLY|OWNER_OCCUPIED|0.9001|0.9500|P60M",
      "rateType": "FIXED",
      "repaymentType": "INTEREST_ONLY",
      "loanPurpose": "OWNER_OCCUPIED",
      "lvrMin": 0.9001,
      "lvrMax": 0.95,
      "fixedTerm": "P60M",
      "points": [
        {
          "date": "2026-05-03",
          "rate": 0.0709,
          "comparisonRate": 0.0735
        },
        {
          "date": "2026-05-06",
          "rate": 0.0709,
          "comparisonRate": 0.0735
        }
      ]
    },
    {
      "key": "FIXED|INTEREST_ONLY|OWNER_OCCUPIED|0.9501|1.0000|P12M",
      "rateType": "FIXED",
      "repaymentType": "INTEREST_ONLY",
      "loanPurpose": "OWNER_OCCUPIED",
      "lvrMin": 0.9501,
      "lvrMax": 1,
      "fixedTerm": "P12M",
      "points": [
        {
          "date": "2026-05-03",
          "rate": 0.0744,
          "comparisonRate": 0.0753
        },
        {
          "date": "2026-05-06",
          "rate": 0.0744,
          "comparisonRate": 0.0753
        }
      ]
    },
    {
      "key": "FIXED|INTEREST_ONLY|OWNER_OCCUPIED|0.9501|1.0000|P24M",
      "rateType": "FIXED",
      "repaymentType": "INTEREST_ONLY",
      "loanPurpose": "OWNER_OCCUPIED",
      "lvrMin": 0.9501,
      "lvrMax": 1,
      "fixedTerm": "P24M",
      "points": [
        {
          "date": "2026-05-03",
          "rate": 0.0689,
          "comparisonRate": 0.0741
        },
        {
          "date": "2026-05-06",
          "rate": 0.0689,
          "comparisonRate": 0.0741
        }
      ]
    },
    {
      "key": "FIXED|INTEREST_ONLY|OWNER_OCCUPIED|0.9501|1.0000|P36M",
      "rateType": "FIXED",
      "repaymentType": "INTEREST_ONLY",
      "loanPurpose": "OWNER_OCCUPIED",
      "lvrMin": 0.9501,
      "lvrMax": 1,
      "fixedTerm": "P36M",
      "points": [
        {
          "date": "2026-05-03",
          "rate": 0.0659,
          "comparisonRate": 0.0727
        },
        {
          "date": "2026-05-06",
          "rate": 0.0659,
          "comparisonRate": 0.0727
        }
      ]
    },
    {
      "key": "FIXED|INTEREST_ONLY|OWNER_OCCUPIED|0.9501|1.0000|P48M",
      "rateType": "FIXED",
      "repaymentType": "INTEREST_ONLY",
      "loanPurpose": "OWNER_OCCUPIED",
      "lvrMin": 0.9501,
      "lvrMax": 1,
      "fixedTerm": "P48M",
      "points": [
        {
          "date": "2026-05-03",
          "rate": 0.0689,
          "comparisonRate": 0.073
        },
        {
          "date": "2026-05-06",
          "rate": 0.0689,
          "comparisonRate": 0.073
        }
      ]
    },
    {
      "key": "FIXED|INTEREST_ONLY|OWNER_OCCUPIED|0.9501|1.0000|P60M",
      "rateType": "FIXED",
      "repaymentType": "INTEREST_ONLY",
      "loanPurpose": "OWNER_OCCUPIED",
      "lvrMin": 0.9501,
      "lvrMax": 1,
      "fixedTerm": "P60M",
      "points": [
        {
          "date": "2026-05-03",
          "rate": 0.0709,
          "comparisonRate": 0.0735
        },
        {
          "date": "2026-05-06",
          "rate": 0.0709,
          "comparisonRate": 0.0735
        }
      ]
    },
    {
      "key": "FIXED|PRINCIPAL_AND_INTEREST|INVESTMENT|0.0000|0.6000|P12M",
      "rateType": "FIXED",
      "repaymentType": "PRINCIPAL_AND_INTEREST",
      "loanPurpose": "INVESTMENT",
      "lvrMin": 0,
      "lvrMax": 0.6,
      "fixedTerm": "P12M",
      "points": [
        {
          "date": "2026-05-03",
          "rate": 0.0674,
          "comparisonRate": 0.0603
        },
        {
          "date": "2026-05-06",
          "rate": 0.0674,
          "comparisonRate": 0.0603
        }
      ]
    },
    {
      "key": "FIXED|PRINCIPAL_AND_INTEREST|INVESTMENT|0.0000|0.6000|P24M",
      "rateType": "FIXED",
      "repaymentType": "PRINCIPAL_AND_INTEREST",
      "loanPurpose": "INVESTMENT",
      "lvrMin": 0,
      "lvrMax": 0.6,
      "fixedTerm": "P24M",
      "points": [
        {
          "date": "2026-05-03",
          "rate": 0.0645,
          "comparisonRate": 0.0605
        },
        {
          "date": "2026-05-06",
          "rate": 0.0645,
          "comparisonRate": 0.0605
        }
      ]
    },
    {
      "key": "FIXED|PRINCIPAL_AND_INTEREST|INVESTMENT|0.0000|0.6000|P36M",
      "rateType": "FIXED",
      "repaymentType": "PRINCIPAL_AND_INTEREST",
      "loanPurpose": "INVESTMENT",
      "lvrMin": 0,
      "lvrMax": 0.6,
      "fixedTerm": "P36M",
      "points": [
        {
          "date": "2026-05-03",
          "rate": 0.0664,
          "comparisonRate": 0.0615
        },
        {
          "date": "2026-05-06",
          "rate": 0.0664,
          "comparisonRate": 0.0615
        }
      ]
    },
    {
      "key": "FIXED|PRINCIPAL_AND_INTEREST|INVESTMENT|0.0000|0.6000|P48M",
      "rateType": "FIXED",
      "repaymentType": "PRINCIPAL_AND_INTEREST",
      "loanPurpose": "INVESTMENT",
      "lvrMin": 0,
      "lvrMax": 0.6,
      "fixedTerm": "P48M",
      "points": [
        {
          "date": "2026-05-03",
          "rate": 0.0694,
          "comparisonRate": 0.0632
        },
        {
          "date": "2026-05-06",
          "rate": 0.0694,
          "comparisonRate": 0.0632
        }
      ]
    },
    {
      "key": "FIXED|PRINCIPAL_AND_INTEREST|INVESTMENT|0.0000|0.6000|P60M",
      "rateType": "FIXED",
      "repaymentType": "PRINCIPAL_AND_INTEREST",
      "loanPurpose": "INVESTMENT",
      "lvrMin": 0,
      "lvrMax": 0.6,
      "fixedTerm": "P60M",
      "points": [
        {
          "date": "2026-05-03",
          "rate": 0.0694,
          "comparisonRate": 0.0639
        },
        {
          "date": "2026-05-06",
          "rate": 0.0694,
          "comparisonRate": 0.0639
        }
      ]
    },
    {
      "key": "FIXED|PRINCIPAL_AND_INTEREST|INVESTMENT|0.6001|0.7000|P12M",
      "rateType": "FIXED",
      "repaymentType": "PRINCIPAL_AND_INTEREST",
      "loanPurpose": "INVESTMENT",
      "lvrMin": 0.6001,
      "lvrMax": 0.7,
      "fixedTerm": "P12M",
      "points": [
        {
          "date": "2026-05-03",
          "rate": 0.0674,
          "comparisonRate": 0.0603
        },
        {
          "date": "2026-05-06",
          "rate": 0.0674,
          "comparisonRate": 0.0603
        }
      ]
    },
    {
      "key": "FIXED|PRINCIPAL_AND_INTEREST|INVESTMENT|0.6001|0.7000|P24M",
      "rateType": "FIXED",
      "repaymentType": "PRINCIPAL_AND_INTEREST",
      "loanPurpose": "INVESTMENT",
      "lvrMin": 0.6001,
      "lvrMax": 0.7,
      "fixedTerm": "P24M",
      "points": [
        {
          "date": "2026-05-03",
          "rate": 0.0645,
          "comparisonRate": 0.0605
        },
        {
          "date": "2026-05-06",
          "rate": 0.0645,
          "comparisonRate": 0.0605
        }
      ]
    },
    {
      "key": "FIXED|PRINCIPAL_AND_INTEREST|INVESTMENT|0.6001|0.7000|P36M",
      "rateType": "FIXED",
      "repaymentType": "PRINCIPAL_AND_INTEREST",
      "loanPurpose": "INVESTMENT",
      "lvrMin": 0.6001,
      "lvrMax": 0.7,
      "fixedTerm": "P36M",
      "points": [
        {
          "date": "2026-05-03",
          "rate": 0.0664,
          "comparisonRate": 0.0615
        },
        {
          "date": "2026-05-06",
          "rate": 0.0664,
          "comparisonRate": 0.0615
        }
      ]
    },
    {
      "key": "FIXED|PRINCIPAL_AND_INTEREST|INVESTMENT|0.6001|0.7000|P48M",
      "rateType": "FIXED",
      "repaymentType": "PRINCIPAL_AND_INTEREST",
      "loanPurpose": "INVESTMENT",
      "lvrMin": 0.6001,
      "lvrMax": 0.7,
      "fixedTerm": "P48M",
      "points": [
        {
          "date": "2026-05-03",
          "rate": 0.0694,
          "comparisonRate": 0.0632
        },
        {
          "date": "2026-05-06",
          "rate": 0.0694,
          "comparisonRate": 0.0632
        }
      ]
    },
    {
      "key": "FIXED|PRINCIPAL_AND_INTEREST|INVESTMENT|0.6001|0.7000|P60M",
      "rateType": "FIXED",
      "repaymentType": "PRINCIPAL_AND_INTEREST",
      "loanPurpose": "INVESTMENT",
      "lvrMin": 0.6001,
      "lvrMax": 0.7,
      "fixedTerm": "P60M",
      "points": [
        {
          "date": "2026-05-03",
          "rate": 0.0694,
          "comparisonRate": 0.0639
        },
        {
          "date": "2026-05-06",
          "rate": 0.0694,
          "comparisonRate": 0.0639
        }
      ]
    },
    {
      "key": "FIXED|PRINCIPAL_AND_INTEREST|INVESTMENT|0.7001|0.8000|P12M",
      "rateType": "FIXED",
      "repaymentType": "PRINCIPAL_AND_INTEREST",
      "loanPurpose": "INVESTMENT",
      "lvrMin": 0.7001,
      "lvrMax": 0.8,
      "fixedTerm": "P12M",
      "points": [
        {
          "date": "2026-05-03",
          "rate": 0.0674,
          "comparisonRate": 0.0608
        },
        {
          "date": "2026-05-06",
          "rate": 0.0674,
          "comparisonRate": 0.0608
        }
      ]
    },
    {
      "key": "FIXED|PRINCIPAL_AND_INTEREST|INVESTMENT|0.7001|0.8000|P24M",
      "rateType": "FIXED",
      "repaymentType": "PRINCIPAL_AND_INTEREST",
      "loanPurpose": "INVESTMENT",
      "lvrMin": 0.7001,
      "lvrMax": 0.8,
      "fixedTerm": "P24M",
      "points": [
        {
          "date": "2026-05-03",
          "rate": 0.0645,
          "comparisonRate": 0.061
        },
        {
          "date": "2026-05-06",
          "rate": 0.0645,
          "comparisonRate": 0.061
        }
      ]
    },
    {
      "key": "FIXED|PRINCIPAL_AND_INTEREST|INVESTMENT|0.7001|0.8000|P36M",
      "rateType": "FIXED",
      "repaymentType": "PRINCIPAL_AND_INTEREST",
      "loanPurpose": "INVESTMENT",
      "lvrMin": 0.7001,
      "lvrMax": 0.8,
      "fixedTerm": "P36M",
      "points": [
        {
          "date": "2026-05-03",
          "rate": 0.0664,
          "comparisonRate": 0.0619
        },
        {
          "date": "2026-05-06",
          "rate": 0.0664,
          "comparisonRate": 0.0619
        }
      ]
    },
    {
      "key": "FIXED|PRINCIPAL_AND_INTEREST|INVESTMENT|0.7001|0.8000|P48M",
      "rateType": "FIXED",
      "repaymentType": "PRINCIPAL_AND_INTEREST",
      "loanPurpose": "INVESTMENT",
      "lvrMin": 0.7001,
      "lvrMax": 0.8,
      "fixedTerm": "P48M",
      "points": [
        {
          "date": "2026-05-03",
          "rate": 0.0694,
          "comparisonRate": 0.0635
        },
        {
          "date": "2026-05-06",
          "rate": 0.0694,
          "comparisonRate": 0.0635
        }
      ]
    },
    {
      "key": "FIXED|PRINCIPAL_AND_INTEREST|INVESTMENT|0.7001|0.8000|P60M",
      "rateType": "FIXED",
      "repaymentType": "PRINCIPAL_AND_INTEREST",
      "loanPurpose": "INVESTMENT",
      "lvrMin": 0.7001,
      "lvrMax": 0.8,
      "fixedTerm": "P60M",
      "points": [
        {
          "date": "2026-05-03",
          "rate": 0.0694,
          "comparisonRate": 0.0643
        },
        {
          "date": "2026-05-06",
          "rate": 0.0694,
          "comparisonRate": 0.0643
        }
      ]
    },
    {
      "key": "FIXED|PRINCIPAL_AND_INTEREST|INVESTMENT|0.8001|0.9000|P12M",
      "rateType": "FIXED",
      "repaymentType": "PRINCIPAL_AND_INTEREST",
      "loanPurpose": "INVESTMENT",
      "lvrMin": 0.8001,
      "lvrMax": 0.9,
      "fixedTerm": "P12M",
      "points": [
        {
          "date": "2026-05-03",
          "rate": 0.0704,
          "comparisonRate": 0.0643
        },
        {
          "date": "2026-05-06",
          "rate": 0.0704,
          "comparisonRate": 0.0643
        }
      ]
    },
    {
      "key": "FIXED|PRINCIPAL_AND_INTEREST|INVESTMENT|0.8001|0.9000|P24M",
      "rateType": "FIXED",
      "repaymentType": "PRINCIPAL_AND_INTEREST",
      "loanPurpose": "INVESTMENT",
      "lvrMin": 0.8001,
      "lvrMax": 0.9,
      "fixedTerm": "P24M",
      "points": [
        {
          "date": "2026-05-03",
          "rate": 0.0665,
          "comparisonRate": 0.0642
        },
        {
          "date": "2026-05-06",
          "rate": 0.0665,
          "comparisonRate": 0.0642
        }
      ]
    },
    {
      "key": "FIXED|PRINCIPAL_AND_INTEREST|INVESTMENT|0.8001|0.9000|P36M",
      "rateType": "FIXED",
      "repaymentType": "PRINCIPAL_AND_INTEREST",
      "loanPurpose": "INVESTMENT",
      "lvrMin": 0.8001,
      "lvrMax": 0.9,
      "fixedTerm": "P36M",
      "points": [
        {
          "date": "2026-05-03",
          "rate": 0.0674,
          "comparisonRate": 0.0647
        },
        {
          "date": "2026-05-06",
          "rate": 0.0674,
          "comparisonRate": 0.0647
        }
      ]
    },
    {
      "key": "FIXED|PRINCIPAL_AND_INTEREST|INVESTMENT|0.8001|0.9000|P48M",
      "rateType": "FIXED",
      "repaymentType": "PRINCIPAL_AND_INTEREST",
      "loanPurpose": "INVESTMENT",
      "lvrMin": 0.8001,
      "lvrMax": 0.9,
      "fixedTerm": "P48M",
      "points": [
        {
          "date": "2026-05-03",
          "rate": 0.0704,
          "comparisonRate": 0.0661
        },
        {
          "date": "2026-05-06",
          "rate": 0.0704,
          "comparisonRate": 0.0661
        }
      ]
    },
    {
      "key": "FIXED|PRINCIPAL_AND_INTEREST|INVESTMENT|0.8001|0.9000|P60M",
      "rateType": "FIXED",
      "repaymentType": "PRINCIPAL_AND_INTEREST",
      "loanPurpose": "INVESTMENT",
      "lvrMin": 0.8001,
      "lvrMax": 0.9,
      "fixedTerm": "P60M",
      "points": [
        {
          "date": "2026-05-03",
          "rate": 0.0704,
          "comparisonRate": 0.0667
        },
        {
          "date": "2026-05-06",
          "rate": 0.0704,
          "comparisonRate": 0.0667
        }
      ]
    },
    {
      "key": "FIXED|PRINCIPAL_AND_INTEREST|INVESTMENT|0.9001|0.9500|P12M",
      "rateType": "FIXED",
      "repaymentType": "PRINCIPAL_AND_INTEREST",
      "loanPurpose": "INVESTMENT",
      "lvrMin": 0.9001,
      "lvrMax": 0.95,
      "fixedTerm": "P12M",
      "points": [
        {
          "date": "2026-05-03",
          "rate": 0.0754,
          "comparisonRate": 0.0799
        },
        {
          "date": "2026-05-06",
          "rate": 0.0754,
          "comparisonRate": 0.0799
        }
      ]
    },
    {
      "key": "FIXED|PRINCIPAL_AND_INTEREST|INVESTMENT|0.9001|0.9500|P24M",
      "rateType": "FIXED",
      "repaymentType": "PRINCIPAL_AND_INTEREST",
      "loanPurpose": "INVESTMENT",
      "lvrMin": 0.9001,
      "lvrMax": 0.95,
      "fixedTerm": "P24M",
      "points": [
        {
          "date": "2026-05-03",
          "rate": 0.074,
          "comparisonRate": 0.0791
        },
        {
          "date": "2026-05-06",
          "rate": 0.074,
          "comparisonRate": 0.0791
        }
      ]
    },
    {
      "key": "FIXED|PRINCIPAL_AND_INTEREST|INVESTMENT|0.9001|0.9500|P36M",
      "rateType": "FIXED",
      "repaymentType": "PRINCIPAL_AND_INTEREST",
      "loanPurpose": "INVESTMENT",
      "lvrMin": 0.9001,
      "lvrMax": 0.95,
      "fixedTerm": "P36M",
      "points": [
        {
          "date": "2026-05-03",
          "rate": 0.0739,
          "comparisonRate": 0.0785
        },
        {
          "date": "2026-05-06",
          "rate": 0.0739,
          "comparisonRate": 0.0785
        }
      ]
    },
    {
      "key": "FIXED|PRINCIPAL_AND_INTEREST|INVESTMENT|0.9001|0.9500|P48M",
      "rateType": "FIXED",
      "repaymentType": "PRINCIPAL_AND_INTEREST",
      "loanPurpose": "INVESTMENT",
      "lvrMin": 0.9001,
      "lvrMax": 0.95,
      "fixedTerm": "P48M",
      "points": [
        {
          "date": "2026-05-03",
          "rate": 0.0764,
          "comparisonRate": 0.0789
        },
        {
          "date": "2026-05-06",
          "rate": 0.0764,
          "comparisonRate": 0.0789
        }
      ]
    },
    {
      "key": "FIXED|PRINCIPAL_AND_INTEREST|INVESTMENT|0.9001|0.9500|P60M",
      "rateType": "FIXED",
      "repaymentType": "PRINCIPAL_AND_INTEREST",
      "loanPurpose": "INVESTMENT",
      "lvrMin": 0.9001,
      "lvrMax": 0.95,
      "fixedTerm": "P60M",
      "points": [
        {
          "date": "2026-05-03",
          "rate": 0.0764,
          "comparisonRate": 0.0787
        },
        {
          "date": "2026-05-06",
          "rate": 0.0764,
          "comparisonRate": 0.0787
        }
      ]
    },
    {
      "key": "FIXED|PRINCIPAL_AND_INTEREST|INVESTMENT|0.9501|1.0000|P12M",
      "rateType": "FIXED",
      "repaymentType": "PRINCIPAL_AND_INTEREST",
      "loanPurpose": "INVESTMENT",
      "lvrMin": 0.9501,
      "lvrMax": 1,
      "fixedTerm": "P12M",
      "points": [
        {
          "date": "2026-05-03",
          "rate": 0.0754,
          "comparisonRate": 0.0799
        },
        {
          "date": "2026-05-06",
          "rate": 0.0754,
          "comparisonRate": 0.0799
        }
      ]
    },
    {
      "key": "FIXED|PRINCIPAL_AND_INTEREST|INVESTMENT|0.9501|1.0000|P24M",
      "rateType": "FIXED",
      "repaymentType": "PRINCIPAL_AND_INTEREST",
      "loanPurpose": "INVESTMENT",
      "lvrMin": 0.9501,
      "lvrMax": 1,
      "fixedTerm": "P24M",
      "points": [
        {
          "date": "2026-05-03",
          "rate": 0.074,
          "comparisonRate": 0.0791
        },
        {
          "date": "2026-05-06",
          "rate": 0.074,
          "comparisonRate": 0.0791
        }
      ]
    },
    {
      "key": "FIXED|PRINCIPAL_AND_INTEREST|INVESTMENT|0.9501|1.0000|P36M",
      "rateType": "FIXED",
      "repaymentType": "PRINCIPAL_AND_INTEREST",
      "loanPurpose": "INVESTMENT",
      "lvrMin": 0.9501,
      "lvrMax": 1,
      "fixedTerm": "P36M",
      "points": [
        {
          "date": "2026-05-03",
          "rate": 0.0739,
          "comparisonRate": 0.0785
        },
        {
          "date": "2026-05-06",
          "rate": 0.0739,
          "comparisonRate": 0.0785
        }
      ]
    },
    {
      "key": "FIXED|PRINCIPAL_AND_INTEREST|INVESTMENT|0.9501|1.0000|P48M",
      "rateType": "FIXED",
      "repaymentType": "PRINCIPAL_AND_INTEREST",
      "loanPurpose": "INVESTMENT",
      "lvrMin": 0.9501,
      "lvrMax": 1,
      "fixedTerm": "P48M",
      "points": [
        {
          "date": "2026-05-03",
          "rate": 0.0764,
          "comparisonRate": 0.0789
        },
        {
          "date": "2026-05-06",
          "rate": 0.0764,
          "comparisonRate": 0.0789
        }
      ]
    },
    {
      "key": "FIXED|PRINCIPAL_AND_INTEREST|INVESTMENT|0.9501|1.0000|P60M",
      "rateType": "FIXED",
      "repaymentType": "PRINCIPAL_AND_INTEREST",
      "loanPurpose": "INVESTMENT",
      "lvrMin": 0.9501,
      "lvrMax": 1,
      "fixedTerm": "P60M",
      "points": [
        {
          "date": "2026-05-03",
          "rate": 0.0764,
          "comparisonRate": 0.0787
        },
        {
          "date": "2026-05-06",
          "rate": 0.0764,
          "comparisonRate": 0.0787
        }
      ]
    },
    {
      "key": "FIXED|PRINCIPAL_AND_INTEREST|OWNER_OCCUPIED|0.0000|0.6000|P12M",
      "rateType": "FIXED",
      "repaymentType": "PRINCIPAL_AND_INTEREST",
      "loanPurpose": "OWNER_OCCUPIED",
      "lvrMin": 0,
      "lvrMax": 0.6,
      "fixedTerm": "P12M",
      "points": [
        {
          "date": "2026-05-03",
          "rate": 0.0654,
          "comparisonRate": 0.0592
        },
        {
          "date": "2026-05-06",
          "rate": 0.0654,
          "comparisonRate": 0.0592
        }
      ]
    },
    {
      "key": "FIXED|PRINCIPAL_AND_INTEREST|OWNER_OCCUPIED|0.0000|0.6000|P24M",
      "rateType": "FIXED",
      "repaymentType": "PRINCIPAL_AND_INTEREST",
      "loanPurpose": "OWNER_OCCUPIED",
      "lvrMin": 0,
      "lvrMax": 0.6,
      "fixedTerm": "P24M",
      "points": [
        {
          "date": "2026-05-03",
          "rate": 0.0629,
          "comparisonRate": 0.0594
        },
        {
          "date": "2026-05-06",
          "rate": 0.0629,
          "comparisonRate": 0.0594
        }
      ]
    },
    {
      "key": "FIXED|PRINCIPAL_AND_INTEREST|OWNER_OCCUPIED|0.0000|0.6000|P36M",
      "rateType": "FIXED",
      "repaymentType": "PRINCIPAL_AND_INTEREST",
      "loanPurpose": "OWNER_OCCUPIED",
      "lvrMin": 0,
      "lvrMax": 0.6,
      "fixedTerm": "P36M",
      "points": [
        {
          "date": "2026-05-03",
          "rate": 0.0644,
          "comparisonRate": 0.0602
        },
        {
          "date": "2026-05-06",
          "rate": 0.0644,
          "comparisonRate": 0.0602
        }
      ]
    },
    {
      "key": "FIXED|PRINCIPAL_AND_INTEREST|OWNER_OCCUPIED|0.0000|0.6000|P48M",
      "rateType": "FIXED",
      "repaymentType": "PRINCIPAL_AND_INTEREST",
      "loanPurpose": "OWNER_OCCUPIED",
      "lvrMin": 0,
      "lvrMax": 0.6,
      "fixedTerm": "P48M",
      "points": [
        {
          "date": "2026-05-03",
          "rate": 0.0674,
          "comparisonRate": 0.0618
        },
        {
          "date": "2026-05-06",
          "rate": 0.0674,
          "comparisonRate": 0.0618
        }
      ]
    },
    {
      "key": "FIXED|PRINCIPAL_AND_INTEREST|OWNER_OCCUPIED|0.0000|0.6000|P60M",
      "rateType": "FIXED",
      "repaymentType": "PRINCIPAL_AND_INTEREST",
      "loanPurpose": "OWNER_OCCUPIED",
      "lvrMin": 0,
      "lvrMax": 0.6,
      "fixedTerm": "P60M",
      "points": [
        {
          "date": "2026-05-03",
          "rate": 0.0674,
          "comparisonRate": 0.0625
        },
        {
          "date": "2026-05-06",
          "rate": 0.0674,
          "comparisonRate": 0.0625
        }
      ]
    },
    {
      "key": "FIXED|PRINCIPAL_AND_INTEREST|OWNER_OCCUPIED|0.6001|0.7000|P12M",
      "rateType": "FIXED",
      "repaymentType": "PRINCIPAL_AND_INTEREST",
      "loanPurpose": "OWNER_OCCUPIED",
      "lvrMin": 0.6001,
      "lvrMax": 0.7,
      "fixedTerm": "P12M",
      "points": [
        {
          "date": "2026-05-03",
          "rate": 0.0654,
          "comparisonRate": 0.0592
        },
        {
          "date": "2026-05-06",
          "rate": 0.0654,
          "comparisonRate": 0.0592
        }
      ]
    },
    {
      "key": "FIXED|PRINCIPAL_AND_INTEREST|OWNER_OCCUPIED|0.6001|0.7000|P24M",
      "rateType": "FIXED",
      "repaymentType": "PRINCIPAL_AND_INTEREST",
      "loanPurpose": "OWNER_OCCUPIED",
      "lvrMin": 0.6001,
      "lvrMax": 0.7,
      "fixedTerm": "P24M",
      "points": [
        {
          "date": "2026-05-03",
          "rate": 0.0629,
          "comparisonRate": 0.0594
        },
        {
          "date": "2026-05-06",
          "rate": 0.0629,
          "comparisonRate": 0.0594
        }
      ]
    },
    {
      "key": "FIXED|PRINCIPAL_AND_INTEREST|OWNER_OCCUPIED|0.6001|0.7000|P36M",
      "rateType": "FIXED",
      "repaymentType": "PRINCIPAL_AND_INTEREST",
      "loanPurpose": "OWNER_OCCUPIED",
      "lvrMin": 0.6001,
      "lvrMax": 0.7,
      "fixedTerm": "P36M",
      "points": [
        {
          "date": "2026-05-03",
          "rate": 0.0644,
          "comparisonRate": 0.0602
        },
        {
          "date": "2026-05-06",
          "rate": 0.0644,
          "comparisonRate": 0.0602
        }
      ]
    },
    {
      "key": "FIXED|PRINCIPAL_AND_INTEREST|OWNER_OCCUPIED|0.6001|0.7000|P48M",
      "rateType": "FIXED",
      "repaymentType": "PRINCIPAL_AND_INTEREST",
      "loanPurpose": "OWNER_OCCUPIED",
      "lvrMin": 0.6001,
      "lvrMax": 0.7,
      "fixedTerm": "P48M",
      "points": [
        {
          "date": "2026-05-03",
          "rate": 0.0674,
          "comparisonRate": 0.0618
        },
        {
          "date": "2026-05-06",
          "rate": 0.0674,
          "comparisonRate": 0.0618
        }
      ]
    },
    {
      "key": "FIXED|PRINCIPAL_AND_INTEREST|OWNER_OCCUPIED|0.6001|0.7000|P60M",
      "rateType": "FIXED",
      "repaymentType": "PRINCIPAL_AND_INTEREST",
      "loanPurpose": "OWNER_OCCUPIED",
      "lvrMin": 0.6001,
      "lvrMax": 0.7,
      "fixedTerm": "P60M",
      "points": [
        {
          "date": "2026-05-03",
          "rate": 0.0674,
          "comparisonRate": 0.0625
        },
        {
          "date": "2026-05-06",
          "rate": 0.0674,
          "comparisonRate": 0.0625
        }
      ]
    },
    {
      "key": "FIXED|PRINCIPAL_AND_INTEREST|OWNER_OCCUPIED|0.7001|0.8000|P12M",
      "rateType": "FIXED",
      "repaymentType": "PRINCIPAL_AND_INTEREST",
      "loanPurpose": "OWNER_OCCUPIED",
      "lvrMin": 0.7001,
      "lvrMax": 0.8,
      "fixedTerm": "P12M",
      "points": [
        {
          "date": "2026-05-03",
          "rate": 0.0654,
          "comparisonRate": 0.0596
        },
        {
          "date": "2026-05-06",
          "rate": 0.0654,
          "comparisonRate": 0.0596
        }
      ]
    },
    {
      "key": "FIXED|PRINCIPAL_AND_INTEREST|OWNER_OCCUPIED|0.7001|0.8000|P24M",
      "rateType": "FIXED",
      "repaymentType": "PRINCIPAL_AND_INTEREST",
      "loanPurpose": "OWNER_OCCUPIED",
      "lvrMin": 0.7001,
      "lvrMax": 0.8,
      "fixedTerm": "P24M",
      "points": [
        {
          "date": "2026-05-03",
          "rate": 0.0629,
          "comparisonRate": 0.0598
        },
        {
          "date": "2026-05-06",
          "rate": 0.0629,
          "comparisonRate": 0.0598
        }
      ]
    },
    {
      "key": "FIXED|PRINCIPAL_AND_INTEREST|OWNER_OCCUPIED|0.7001|0.8000|P36M",
      "rateType": "FIXED",
      "repaymentType": "PRINCIPAL_AND_INTEREST",
      "loanPurpose": "OWNER_OCCUPIED",
      "lvrMin": 0.7001,
      "lvrMax": 0.8,
      "fixedTerm": "P36M",
      "points": [
        {
          "date": "2026-05-03",
          "rate": 0.0644,
          "comparisonRate": 0.0605
        },
        {
          "date": "2026-05-06",
          "rate": 0.0644,
          "comparisonRate": 0.0605
        }
      ]
    },
    {
      "key": "FIXED|PRINCIPAL_AND_INTEREST|OWNER_OCCUPIED|0.7001|0.8000|P48M",
      "rateType": "FIXED",
      "repaymentType": "PRINCIPAL_AND_INTEREST",
      "loanPurpose": "OWNER_OCCUPIED",
      "lvrMin": 0.7001,
      "lvrMax": 0.8,
      "fixedTerm": "P48M",
      "points": [
        {
          "date": "2026-05-03",
          "rate": 0.0674,
          "comparisonRate": 0.0621
        },
        {
          "date": "2026-05-06",
          "rate": 0.0674,
          "comparisonRate": 0.0621
        }
      ]
    },
    {
      "key": "FIXED|PRINCIPAL_AND_INTEREST|OWNER_OCCUPIED|0.7001|0.8000|P60M",
      "rateType": "FIXED",
      "repaymentType": "PRINCIPAL_AND_INTEREST",
      "loanPurpose": "OWNER_OCCUPIED",
      "lvrMin": 0.7001,
      "lvrMax": 0.8,
      "fixedTerm": "P60M",
      "points": [
        {
          "date": "2026-05-03",
          "rate": 0.0674,
          "comparisonRate": 0.0627
        },
        {
          "date": "2026-05-06",
          "rate": 0.0674,
          "comparisonRate": 0.0627
        }
      ]
    },
    {
      "key": "FIXED|PRINCIPAL_AND_INTEREST|OWNER_OCCUPIED|0.8001|0.9000|P12M",
      "rateType": "FIXED",
      "repaymentType": "PRINCIPAL_AND_INTEREST",
      "loanPurpose": "OWNER_OCCUPIED",
      "lvrMin": 0.8001,
      "lvrMax": 0.9,
      "fixedTerm": "P12M",
      "points": [
        {
          "date": "2026-05-03",
          "rate": 0.0689,
          "comparisonRate": 0.0619
        },
        {
          "date": "2026-05-06",
          "rate": 0.0689,
          "comparisonRate": 0.0619
        }
      ]
    },
    {
      "key": "FIXED|PRINCIPAL_AND_INTEREST|OWNER_OCCUPIED|0.8001|0.9000|P24M",
      "rateType": "FIXED",
      "repaymentType": "PRINCIPAL_AND_INTEREST",
      "loanPurpose": "OWNER_OCCUPIED",
      "lvrMin": 0.8001,
      "lvrMax": 0.9,
      "fixedTerm": "P24M",
      "points": [
        {
          "date": "2026-05-03",
          "rate": 0.0664,
          "comparisonRate": 0.0621
        },
        {
          "date": "2026-05-06",
          "rate": 0.0664,
          "comparisonRate": 0.0621
        }
      ]
    },
    {
      "key": "FIXED|PRINCIPAL_AND_INTEREST|OWNER_OCCUPIED|0.8001|0.9000|P36M",
      "rateType": "FIXED",
      "repaymentType": "PRINCIPAL_AND_INTEREST",
      "loanPurpose": "OWNER_OCCUPIED",
      "lvrMin": 0.8001,
      "lvrMax": 0.9,
      "fixedTerm": "P36M",
      "points": [
        {
          "date": "2026-05-03",
          "rate": 0.0669,
          "comparisonRate": 0.0628
        },
        {
          "date": "2026-05-06",
          "rate": 0.0669,
          "comparisonRate": 0.0628
        }
      ]
    },
    {
      "key": "FIXED|PRINCIPAL_AND_INTEREST|OWNER_OCCUPIED|0.8001|0.9000|P48M",
      "rateType": "FIXED",
      "repaymentType": "PRINCIPAL_AND_INTEREST",
      "loanPurpose": "OWNER_OCCUPIED",
      "lvrMin": 0.8001,
      "lvrMax": 0.9,
      "fixedTerm": "P48M",
      "points": [
        {
          "date": "2026-05-03",
          "rate": 0.0699,
          "comparisonRate": 0.0644
        },
        {
          "date": "2026-05-06",
          "rate": 0.0699,
          "comparisonRate": 0.0644
        }
      ]
    },
    {
      "key": "FIXED|PRINCIPAL_AND_INTEREST|OWNER_OCCUPIED|0.8001|0.9000|P60M",
      "rateType": "FIXED",
      "repaymentType": "PRINCIPAL_AND_INTEREST",
      "loanPurpose": "OWNER_OCCUPIED",
      "lvrMin": 0.8001,
      "lvrMax": 0.9,
      "fixedTerm": "P60M",
      "points": [
        {
          "date": "2026-05-03",
          "rate": 0.0699,
          "comparisonRate": 0.065
        },
        {
          "date": "2026-05-06",
          "rate": 0.0699,
          "comparisonRate": 0.065
        }
      ]
    },
    {
      "key": "FIXED|PRINCIPAL_AND_INTEREST|OWNER_OCCUPIED|0.9001|0.9500|P12M",
      "rateType": "FIXED",
      "repaymentType": "PRINCIPAL_AND_INTEREST",
      "loanPurpose": "OWNER_OCCUPIED",
      "lvrMin": 0.9001,
      "lvrMax": 0.95,
      "fixedTerm": "P12M",
      "points": [
        {
          "date": "2026-05-03",
          "rate": 0.0784,
          "comparisonRate": 0.0757
        },
        {
          "date": "2026-05-06",
          "rate": 0.0784,
          "comparisonRate": 0.0757
        }
      ]
    },
    {
      "key": "FIXED|PRINCIPAL_AND_INTEREST|OWNER_OCCUPIED|0.9001|0.9500|P24M",
      "rateType": "FIXED",
      "repaymentType": "PRINCIPAL_AND_INTEREST",
      "loanPurpose": "OWNER_OCCUPIED",
      "lvrMin": 0.9001,
      "lvrMax": 0.95,
      "fixedTerm": "P24M",
      "points": [
        {
          "date": "2026-05-03",
          "rate": 0.0724,
          "comparisonRate": 0.0748
        },
        {
          "date": "2026-05-06",
          "rate": 0.0724,
          "comparisonRate": 0.0748
        }
      ]
    },
    {
      "key": "FIXED|PRINCIPAL_AND_INTEREST|OWNER_OCCUPIED|0.9001|0.9500|P36M",
      "rateType": "FIXED",
      "repaymentType": "PRINCIPAL_AND_INTEREST",
      "loanPurpose": "OWNER_OCCUPIED",
      "lvrMin": 0.9001,
      "lvrMax": 0.95,
      "fixedTerm": "P36M",
      "points": [
        {
          "date": "2026-05-03",
          "rate": 0.0734,
          "comparisonRate": 0.0748
        },
        {
          "date": "2026-05-06",
          "rate": 0.0734,
          "comparisonRate": 0.0748
        }
      ]
    },
    {
      "key": "FIXED|PRINCIPAL_AND_INTEREST|OWNER_OCCUPIED|0.9001|0.9500|P48M",
      "rateType": "FIXED",
      "repaymentType": "PRINCIPAL_AND_INTEREST",
      "loanPurpose": "OWNER_OCCUPIED",
      "lvrMin": 0.9001,
      "lvrMax": 0.95,
      "fixedTerm": "P48M",
      "points": [
        {
          "date": "2026-05-03",
          "rate": 0.0749,
          "comparisonRate": 0.0752
        },
        {
          "date": "2026-05-06",
          "rate": 0.0749,
          "comparisonRate": 0.0752
        }
      ]
    },
    {
      "key": "FIXED|PRINCIPAL_AND_INTEREST|OWNER_OCCUPIED|0.9001|0.9500|P60M",
      "rateType": "FIXED",
      "repaymentType": "PRINCIPAL_AND_INTEREST",
      "loanPurpose": "OWNER_OCCUPIED",
      "lvrMin": 0.9001,
      "lvrMax": 0.95,
      "fixedTerm": "P60M",
      "points": [
        {
          "date": "2026-05-03",
          "rate": 0.0764,
          "comparisonRate": 0.0759
        },
        {
          "date": "2026-05-06",
          "rate": 0.0764,
          "comparisonRate": 0.0759
        }
      ]
    },
    {
      "key": "FIXED|PRINCIPAL_AND_INTEREST|OWNER_OCCUPIED|0.9501|1.0000|P12M",
      "rateType": "FIXED",
      "repaymentType": "PRINCIPAL_AND_INTEREST",
      "loanPurpose": "OWNER_OCCUPIED",
      "lvrMin": 0.9501,
      "lvrMax": 1,
      "fixedTerm": "P12M",
      "points": [
        {
          "date": "2026-05-03",
          "rate": 0.0784,
          "comparisonRate": 0.0757
        },
        {
          "date": "2026-05-06",
          "rate": 0.0784,
          "comparisonRate": 0.0757
        }
      ]
    },
    {
      "key": "FIXED|PRINCIPAL_AND_INTEREST|OWNER_OCCUPIED|0.9501|1.0000|P24M",
      "rateType": "FIXED",
      "repaymentType": "PRINCIPAL_AND_INTEREST",
      "loanPurpose": "OWNER_OCCUPIED",
      "lvrMin": 0.9501,
      "lvrMax": 1,
      "fixedTerm": "P24M",
      "points": [
        {
          "date": "2026-05-03",
          "rate": 0.0724,
          "comparisonRate": 0.0748
        },
        {
          "date": "2026-05-06",
          "rate": 0.0724,
          "comparisonRate": 0.0748
        }
      ]
    },
    {
      "key": "FIXED|PRINCIPAL_AND_INTEREST|OWNER_OCCUPIED|0.9501|1.0000|P36M",
      "rateType": "FIXED",
      "repaymentType": "PRINCIPAL_AND_INTEREST",
      "loanPurpose": "OWNER_OCCUPIED",
      "lvrMin": 0.9501,
      "lvrMax": 1,
      "fixedTerm": "P36M",
      "points": [
        {
          "date": "2026-05-03",
          "rate": 0.0734,
          "comparisonRate": 0.0748
        },
        {
          "date": "2026-05-06",
          "rate": 0.0734,
          "comparisonRate": 0.0748
        }
      ]
    },
    {
      "key": "FIXED|PRINCIPAL_AND_INTEREST|OWNER_OCCUPIED|0.9501|1.0000|P48M",
      "rateType": "FIXED",
      "repaymentType": "PRINCIPAL_AND_INTEREST",
      "loanPurpose": "OWNER_OCCUPIED",
      "lvrMin": 0.9501,
      "lvrMax": 1,
      "fixedTerm": "P48M",
      "points": [
        {
          "date": "2026-05-03",
          "rate": 0.0749,
          "comparisonRate": 0.0752
        },
        {
          "date": "2026-05-06",
          "rate": 0.0749,
          "comparisonRate": 0.0752
        }
      ]
    },
    {
      "key": "FIXED|PRINCIPAL_AND_INTEREST|OWNER_OCCUPIED|0.9501|1.0000|P60M",
      "rateType": "FIXED",
      "repaymentType": "PRINCIPAL_AND_INTEREST",
      "loanPurpose": "OWNER_OCCUPIED",
      "lvrMin": 0.9501,
      "lvrMax": 1,
      "fixedTerm": "P60M",
      "points": [
        {
          "date": "2026-05-03",
          "rate": 0.0764,
          "comparisonRate": 0.0759
        },
        {
          "date": "2026-05-06",
          "rate": 0.0764,
          "comparisonRate": 0.0759
        }
      ]
    },
    {
      "key": "VARIABLE|INTEREST_ONLY|INVESTMENT|0.0000|0.6000|",
      "rateType": "VARIABLE",
      "repaymentType": "INTEREST_ONLY",
      "loanPurpose": "INVESTMENT",
      "lvrMin": 0,
      "lvrMax": 0.6,
      "points": [
        {
          "date": "2026-05-03",
          "rate": 0.0614,
          "comparisonRate": 0.0603
        },
        {
          "date": "2026-05-06",
          "rate": 0.0614,
          "comparisonRate": 0.0603
        }
      ]
    },
    {
      "key": "VARIABLE|INTEREST_ONLY|INVESTMENT|0.6001|0.7000|",
      "rateType": "VARIABLE",
      "repaymentType": "INTEREST_ONLY",
      "loanPurpose": "INVESTMENT",
      "lvrMin": 0.6001,
      "lvrMax": 0.7,
      "points": [
        {
          "date": "2026-05-03",
          "rate": 0.0614,
          "comparisonRate": 0.0603
        },
        {
          "date": "2026-05-06",
          "rate": 0.0614,
          "comparisonRate": 0.0603
        }
      ]
    },
    {
      "key": "VARIABLE|INTEREST_ONLY|INVESTMENT|0.7001|0.8000|",
      "rateType": "VARIABLE",
      "repaymentType": "INTEREST_ONLY",
      "loanPurpose": "INVESTMENT",
      "lvrMin": 0.7001,
      "lvrMax": 0.8,
      "points": [
        {
          "date": "2026-05-03",
          "rate": 0.0619,
          "comparisonRate": 0.0609
        },
        {
          "date": "2026-05-06",
          "rate": 0.0619,
          "comparisonRate": 0.0609
        }
      ]
    },
    {
      "key": "VARIABLE|INTEREST_ONLY|INVESTMENT|0.8001|0.9000|",
      "rateType": "VARIABLE",
      "repaymentType": "INTEREST_ONLY",
      "loanPurpose": "INVESTMENT",
      "lvrMin": 0.8001,
      "lvrMax": 0.9,
      "points": [
        {
          "date": "2026-05-03",
          "rate": 0.0649,
          "comparisonRate": 0.0642
        },
        {
          "date": "2026-05-06",
          "rate": 0.0649,
          "comparisonRate": 0.0642
        }
      ]
    },
    {
      "key": "VARIABLE|INTEREST_ONLY|INVESTMENT|0.9001|0.9500|",
      "rateType": "VARIABLE",
      "repaymentType": "INTEREST_ONLY",
      "loanPurpose": "INVESTMENT",
      "lvrMin": 0.9001,
      "lvrMax": 0.95,
      "points": [
        {
          "date": "2026-05-03",
          "rate": 0.0848,
          "comparisonRate": 0.0825
        },
        {
          "date": "2026-05-06",
          "rate": 0.0848,
          "comparisonRate": 0.0825
        }
      ]
    },
    {
      "key": "VARIABLE|INTEREST_ONLY|INVESTMENT|0.9501|1.0000|",
      "rateType": "VARIABLE",
      "repaymentType": "INTEREST_ONLY",
      "loanPurpose": "INVESTMENT",
      "lvrMin": 0.9501,
      "lvrMax": 1,
      "points": [
        {
          "date": "2026-05-03",
          "rate": 0.0848,
          "comparisonRate": 0.0825
        },
        {
          "date": "2026-05-06",
          "rate": 0.0848,
          "comparisonRate": 0.0825
        }
      ]
    },
    {
      "key": "VARIABLE|INTEREST_ONLY|OWNER_OCCUPIED|0.0000|0.6000|",
      "rateType": "VARIABLE",
      "repaymentType": "INTEREST_ONLY",
      "loanPurpose": "OWNER_OCCUPIED",
      "lvrMin": 0,
      "lvrMax": 0.6,
      "points": [
        {
          "date": "2026-05-03",
          "rate": 0.0792,
          "comparisonRate": 0.0676
        },
        {
          "date": "2026-05-04",
          "rate": 0.0792,
          "comparisonRate": 0.0809
        },
        {
          "date": "2026-05-06",
          "rate": 0.0792,
          "comparisonRate": 0.0809
        }
      ]
    },
    {
      "key": "VARIABLE|INTEREST_ONLY|OWNER_OCCUPIED|0.6001|0.7000|",
      "rateType": "VARIABLE",
      "repaymentType": "INTEREST_ONLY",
      "loanPurpose": "OWNER_OCCUPIED",
      "lvrMin": 0.6001,
      "lvrMax": 0.7,
      "points": [
        {
          "date": "2026-05-03",
          "rate": 0.0792,
          "comparisonRate": 0.0676
        },
        {
          "date": "2026-05-06",
          "rate": 0.0792,
          "comparisonRate": 0.0676
        }
      ]
    },
    {
      "key": "VARIABLE|INTEREST_ONLY|OWNER_OCCUPIED|0.7001|0.8000|",
      "rateType": "VARIABLE",
      "repaymentType": "INTEREST_ONLY",
      "loanPurpose": "OWNER_OCCUPIED",
      "lvrMin": 0.7001,
      "lvrMax": 0.8,
      "points": [
        {
          "date": "2026-05-03",
          "rate": 0.0792,
          "comparisonRate": 0.0809
        },
        {
          "date": "2026-05-05",
          "rate": 0.0792,
          "comparisonRate": 0.0678
        },
        {
          "date": "2026-05-06",
          "rate": 0.0792,
          "comparisonRate": 0.0678
        }
      ]
    },
    {
      "key": "VARIABLE|INTEREST_ONLY|OWNER_OCCUPIED|0.8001|0.9000|",
      "rateType": "VARIABLE",
      "repaymentType": "INTEREST_ONLY",
      "loanPurpose": "OWNER_OCCUPIED",
      "lvrMin": 0.8001,
      "lvrMax": 0.9,
      "points": [
        {
          "date": "2026-05-03",
          "rate": 0.0823,
          "comparisonRate": 0.0705
        },
        {
          "date": "2026-05-04",
          "rate": 0.0823,
          "comparisonRate": 0.0837
        },
        {
          "date": "2026-05-05",
          "rate": 0.0823,
          "comparisonRate": 0.0705
        },
        {
          "date": "2026-05-06",
          "rate": 0.0823,
          "comparisonRate": 0.0837
        }
      ]
    },
    {
      "key": "VARIABLE|INTEREST_ONLY|OWNER_OCCUPIED|0.9001|0.9500|",
      "rateType": "VARIABLE",
      "repaymentType": "INTEREST_ONLY",
      "loanPurpose": "OWNER_OCCUPIED",
      "lvrMin": 0.9001,
      "lvrMax": 0.95,
      "points": [
        {
          "date": "2026-05-03",
          "rate": 0.0823,
          "comparisonRate": 0.0837
        },
        {
          "date": "2026-05-04",
          "rate": 0.0823,
          "comparisonRate": 0.0785
        },
        {
          "date": "2026-05-05",
          "rate": 0.0823,
          "comparisonRate": 0.0837
        },
        {
          "date": "2026-05-06",
          "rate": 0.0823,
          "comparisonRate": 0.0785
        }
      ]
    },
    {
      "key": "VARIABLE|INTEREST_ONLY|OWNER_OCCUPIED|0.9501|1.0000|",
      "rateType": "VARIABLE",
      "repaymentType": "INTEREST_ONLY",
      "loanPurpose": "OWNER_OCCUPIED",
      "lvrMin": 0.9501,
      "lvrMax": 1,
      "points": [
        {
          "date": "2026-05-03",
          "rate": 0.0823,
          "comparisonRate": 0.0785
        },
        {
          "date": "2026-05-04",
          "rate": 0.0823,
          "comparisonRate": 0.0837
        },
        {
          "date": "2026-05-05",
          "rate": 0.0823,
          "comparisonRate": 0.0785
        },
        {
          "date": "2026-05-06",
          "rate": 0.0823,
          "comparisonRate": 0.0837
        }
      ]
    },
    {
      "key": "VARIABLE|PRINCIPAL_AND_INTEREST|INVESTMENT|0.0000|0.6000|",
      "rateType": "VARIABLE",
      "repaymentType": "PRINCIPAL_AND_INTEREST",
      "loanPurpose": "INVESTMENT",
      "lvrMin": 0,
      "lvrMax": 0.6,
      "points": [
        {
          "date": "2026-05-03",
          "rate": 0.0593,
          "comparisonRate": 0.0595
        },
        {
          "date": "2026-05-06",
          "rate": 0.0593,
          "comparisonRate": 0.0595
        }
      ]
    },
    {
      "key": "VARIABLE|PRINCIPAL_AND_INTEREST|INVESTMENT|0.6001|0.7000|",
      "rateType": "VARIABLE",
      "repaymentType": "PRINCIPAL_AND_INTEREST",
      "loanPurpose": "INVESTMENT",
      "lvrMin": 0.6001,
      "lvrMax": 0.7,
      "points": [
        {
          "date": "2026-05-03",
          "rate": 0.0593,
          "comparisonRate": 0.0595
        },
        {
          "date": "2026-05-06",
          "rate": 0.0593,
          "comparisonRate": 0.0595
        }
      ]
    },
    {
      "key": "VARIABLE|PRINCIPAL_AND_INTEREST|INVESTMENT|0.7001|0.8000|",
      "rateType": "VARIABLE",
      "repaymentType": "PRINCIPAL_AND_INTEREST",
      "loanPurpose": "INVESTMENT",
      "lvrMin": 0.7001,
      "lvrMax": 0.8,
      "points": [
        {
          "date": "2026-05-03",
          "rate": 0.0599,
          "comparisonRate": 0.0601
        },
        {
          "date": "2026-05-06",
          "rate": 0.0599,
          "comparisonRate": 0.0601
        }
      ]
    },
    {
      "key": "VARIABLE|PRINCIPAL_AND_INTEREST|INVESTMENT|0.8001|0.9000|",
      "rateType": "VARIABLE",
      "repaymentType": "PRINCIPAL_AND_INTEREST",
      "loanPurpose": "INVESTMENT",
      "lvrMin": 0.8001,
      "lvrMax": 0.9,
      "points": [
        {
          "date": "2026-05-03",
          "rate": 0.0634,
          "comparisonRate": 0.0636
        },
        {
          "date": "2026-05-06",
          "rate": 0.0634,
          "comparisonRate": 0.0636
        }
      ]
    },
    {
      "key": "VARIABLE|PRINCIPAL_AND_INTEREST|INVESTMENT|0.9001|0.9500|",
      "rateType": "VARIABLE",
      "repaymentType": "PRINCIPAL_AND_INTEREST",
      "loanPurpose": "INVESTMENT",
      "lvrMin": 0.9001,
      "lvrMax": 0.95,
      "points": [
        {
          "date": "2026-05-03",
          "rate": 0.0803,
          "comparisonRate": 0.0805
        },
        {
          "date": "2026-05-06",
          "rate": 0.0803,
          "comparisonRate": 0.0805
        }
      ]
    },
    {
      "key": "VARIABLE|PRINCIPAL_AND_INTEREST|INVESTMENT|0.9501|1.0000|",
      "rateType": "VARIABLE",
      "repaymentType": "PRINCIPAL_AND_INTEREST",
      "loanPurpose": "INVESTMENT",
      "lvrMin": 0.9501,
      "lvrMax": 1,
      "points": [
        {
          "date": "2026-05-03",
          "rate": 0.0803,
          "comparisonRate": 0.0805
        },
        {
          "date": "2026-05-06",
          "rate": 0.0803,
          "comparisonRate": 0.0805
        }
      ]
    },
    {
      "key": "VARIABLE|PRINCIPAL_AND_INTEREST|OWNER_OCCUPIED|0.0000|0.6000|",
      "rateType": "VARIABLE",
      "repaymentType": "PRINCIPAL_AND_INTEREST",
      "loanPurpose": "OWNER_OCCUPIED",
      "lvrMin": 0,
      "lvrMax": 0.6,
      "points": [
        {
          "date": "2026-05-03",
          "rate": 0.082,
          "comparisonRate": 0.0822
        },
        {
          "date": "2026-05-06",
          "rate": 0.082,
          "comparisonRate": 0.0822
        }
      ]
    },
    {
      "key": "VARIABLE|PRINCIPAL_AND_INTEREST|OWNER_OCCUPIED|0.6001|0.7000|",
      "rateType": "VARIABLE",
      "repaymentType": "PRINCIPAL_AND_INTEREST",
      "loanPurpose": "OWNER_OCCUPIED",
      "lvrMin": 0.6001,
      "lvrMax": 0.7,
      "points": [
        {
          "date": "2026-05-03",
          "rate": 0.082,
          "comparisonRate": 0.0822
        },
        {
          "date": "2026-05-06",
          "rate": 0.082,
          "comparisonRate": 0.0822
        }
      ]
    },
    {
      "key": "VARIABLE|PRINCIPAL_AND_INTEREST|OWNER_OCCUPIED|0.7001|0.8000|",
      "rateType": "VARIABLE",
      "repaymentType": "PRINCIPAL_AND_INTEREST",
      "loanPurpose": "OWNER_OCCUPIED",
      "lvrMin": 0.7001,
      "lvrMax": 0.8,
      "points": [
        {
          "date": "2026-05-03",
          "rate": 0.082,
          "comparisonRate": 0.0822
        },
        {
          "date": "2026-05-06",
          "rate": 0.082,
          "comparisonRate": 0.0822
        }
      ]
    },
    {
      "key": "VARIABLE|PRINCIPAL_AND_INTEREST|OWNER_OCCUPIED|0.8001|0.9000|",
      "rateType": "VARIABLE",
      "repaymentType": "PRINCIPAL_AND_INTEREST",
      "loanPurpose": "OWNER_OCCUPIED",
      "lvrMin": 0.8001,
      "lvrMax": 0.9,
      "points": [
        {
          "date": "2026-05-03",
          "rate": 0.0846,
          "comparisonRate": 0.0848
        },
        {
          "date": "2026-05-06",
          "rate": 0.0846,
          "comparisonRate": 0.0848
        }
      ]
    },
    {
      "key": "VARIABLE|PRINCIPAL_AND_INTEREST|OWNER_OCCUPIED|0.9001|0.9500|",
      "rateType": "VARIABLE",
      "repaymentType": "PRINCIPAL_AND_INTEREST",
      "loanPurpose": "OWNER_OCCUPIED",
      "lvrMin": 0.9001,
      "lvrMax": 0.95,
      "points": [
        {
          "date": "2026-05-03",
          "rate": 0.0846,
          "comparisonRate": 0.0848
        },
        {
          "date": "2026-05-06",
          "rate": 0.0846,
          "comparisonRate": 0.0848
        }
      ]
    },
    {
      "key": "VARIABLE|PRINCIPAL_AND_INTEREST|OWNER_OCCUPIED|0.9501|1.0000|",
      "rateType": "VARIABLE",
      "repaymentType": "PRINCIPAL_AND_INTEREST",
      "loanPurpose": "OWNER_OCCUPIED",
      "lvrMin": 0.9501,
      "lvrMax": 1,
      "points": [
        {
          "date": "2026-05-03",
          "rate": 0.0846,
          "comparisonRate": 0.0848
        },
        {
          "date": "2026-05-06",
          "rate": 0.0846,
          "comparisonRate": 0.0848
        }
      ]
    }
  ]
}
