{
  "key": "qbank-2yearfixedhomeloan-2668fc9c",
  "bankName": "QBANK",
  "productName": "2 Year Fixed Home Loan",
  "productId": "2YearFixedHomeLoan",
  "firstDate": "2026-05-03",
  "lastDate": "2026-05-03",
  "variants": [
    {
      "key": "FIXED|PRINCIPAL_AND_INTEREST|OWNER_OCCUPIED|0.0000|0.9500|P2Y",
      "rateType": "FIXED",
      "repaymentType": "PRINCIPAL_AND_INTEREST",
      "loanPurpose": "OWNER_OCCUPIED",
      "lvrMin": 0,
      "lvrMax": 0.949999,
      "fixedTerm": "P2Y",
      "points": [
        {
          "date": "2026-05-03",
          "rate": 0.0639,
          "comparisonRate": 0.0756
        }
      ]
    },
    {
      "key": "FIXED|UNCONSTRAINED|INVESTMENT|0.0000|0.9500|P2Y",
      "rateType": "FIXED",
      "repaymentType": "UNCONSTRAINED",
      "loanPurpose": "INVESTMENT",
      "lvrMin": 0,
      "lvrMax": 0.949999,
      "fixedTerm": "P2Y",
      "points": [
        {
          "date": "2026-05-03",
          "rate": 0.0659,
          "comparisonRate": 0.0793
        }
      ]
    }
  ]
}
