{"generatedAt":"2026-05-02T07:24:47Z","snapshotCount":47,"historySpanDays":13.1,"outlierFloor":0.04,"summary":{"lowestVariable":0.0554,"lowestFixed":0.0584,"avgRate":0.0645,"medianRateOOPI":0.0589,"bankCount":17,"rateCount":723,"variableCount":269,"fixedCount":454,"lowerCount":9009,"higherCount":27618,"flatCount":64500},"timeline":[{"date":"2026-04-19T05:18:36Z","avgVariable":0.0668,"avgFixed":0.066,"lowestVariable":0.0424,"lowestFixed":0.0549,"bankCount":64,"rateCount":2423},{"date":"2026-04-19T12:46:24Z","avgVariable":0.0668,"avgFixed":0.066,"lowestVariable":0.0424,"lowestFixed":0.0549,"bankCount":63,"rateCount":2418},{"date":"2026-04-19T18:40:37Z","avgVariable":0.0668,"avgFixed":0.066,"lowestVariable":0.0424,"lowestFixed":0.0549,"bankCount":64,"rateCount":2425},{"date":"2026-04-20T02:04:37Z","avgVariable":0.0668,"avgFixed":0.066,"lowestVariable":0.0424,"lowestFixed":0.0549,"bankCount":63,"rateCount":2409},{"date":"2026-04-20T07:57:51Z","avgVariable":0.0669,"avgFixed":0.066,"lowestVariable":0.0424,"lowestFixed":0.0549,"bankCount":63,"rateCount":2407},{"date":"2026-04-20T13:16:56Z","avgVariable":0.0668,"avgFixed":0.066,"lowestVariable":0.0424,"lowestFixed":0.0549,"bankCount":63,"rateCount":2409},{"date":"2026-04-20T18:58:29Z","avgVariable":0.0669,"avgFixed":0.066,"lowestVariable":0.0424,"lowestFixed":0.0549,"bankCount":63,"rateCount":2407},{"date":"2026-04-21T02:00:04Z","avgVariable":0.0669,"avgFixed":0.066,"lowestVariable":0.0424,"lowestFixed":0.0549,"bankCount":63,"rateCount":2411},{"date":"2026-04-21T07:27:52Z","avgVariable":0.0669,"avgFixed":0.066,"lowestVariable":0.0424,"lowestFixed":0.0549,"bankCount":63,"rateCount":2419},{"date":"2026-04-21T13:10:25Z","avgVariable":0.0672,"avgFixed":0.0661,"lowestVariable":0.0424,"lowestFixed":0.0549,"bankCount":60,"rateCount":2279},{"date":"2026-04-21T19:04:48Z","avgVariable":0.0672,"avgFixed":0.0664,"lowestVariable":0.0424,"lowestFixed":0.0549,"bankCount":64,"rateCount":2589},{"date":"2026-04-22T01:58:36Z","avgVariable":0.0669,"avgFixed":0.0661,"lowestVariable":0.0424,"lowestFixed":0.0559,"bankCount":63,"rateCount":2419},{"date":"2026-04-22T07:25:40Z","avgVariable":0.0669,"avgFixed":0.0661,"lowestVariable":0.0424,"lowestFixed":0.0559,"bankCount":63,"rateCount":2419},{"date":"2026-04-22T13:14:14Z","avgVariable":0.0669,"avgFixed":0.0661,"lowestVariable":0.0424,"lowestFixed":0.0559,"bankCount":63,"rateCount":2417},{"date":"2026-04-22T19:06:17Z","avgVariable":0.0678,"avgFixed":0.0663,"lowestVariable":0.0554,"lowestFixed":0.0559,"bankCount":49,"rateCount":1989},{"date":"2026-04-23T02:02:58Z","avgVariable":0.0669,"avgFixed":0.0661,"lowestVariable":0.0424,"lowestFixed":0.0559,"bankCount":63,"rateCount":2415},{"date":"2026-04-23T07:28:18Z","avgVariable":0.0669,"avgFixed":0.0661,"lowestVariable":0.0424,"lowestFixed":0.0559,"bankCount":62,"rateCount":2414},{"date":"2026-04-23T13:12:16Z","avgVariable":0.0657,"avgFixed":0.0661,"lowestVariable":0.0424,"lowestFixed":0.0559,"bankCount":62,"rateCount":2309},{"date":"2026-04-23T19:02:24Z","avgVariable":0.0657,"avgFixed":0.0661,"lowestVariable":0.0424,"lowestFixed":0.0559,"bankCount":63,"rateCount":2349},{"date":"2026-04-24T02:02:51Z","avgVariable":0.0657,"avgFixed":0.0661,"lowestVariable":0.0424,"lowestFixed":0.0559,"bankCount":62,"rateCount":2307},{"date":"2026-04-24T07:54:16Z","avgVariable":0.0656,"avgFixed":0.0661,"lowestVariable":0.0424,"lowestFixed":0.0559,"bankCount":62,"rateCount":2311},{"date":"2026-04-24T13:09:03Z","avgVariable":0.0656,"avgFixed":0.0661,"lowestVariable":0.0424,"lowestFixed":0.0559,"bankCount":62,"rateCount":2311},{"date":"2026-04-24T18:42:14Z","avgVariable":0.0656,"avgFixed":0.0661,"lowestVariable":0.0544,"lowestFixed":0.0559,"bankCount":61,"rateCount":2337},{"date":"2026-04-25T01:52:30Z","avgVariable":0.0656,"avgFixed":0.0661,"lowestVariable":0.0424,"lowestFixed":0.0559,"bankCount":62,"rateCount":2311},{"date":"2026-04-25T07:07:28Z","avgVariable":0.0656,"avgFixed":0.0661,"lowestVariable":0.0424,"lowestFixed":0.0559,"bankCount":62,"rateCount":2311},{"date":"2026-04-25T12:47:59Z","avgVariable":0.0656,"avgFixed":0.0661,"lowestVariable":0.0424,"lowestFixed":0.0559,"bankCount":62,"rateCount":2311},{"date":"2026-04-25T18:42:02Z","avgVariable":0.0656,"avgFixed":0.0661,"lowestVariable":0.0424,"lowestFixed":0.0559,"bankCount":61,"rateCount":2310},{"date":"2026-04-26T02:06:23Z","avgVariable":0.0656,"avgFixed":0.0661,"lowestVariable":0.0424,"lowestFixed":0.0559,"bankCount":62,"rateCount":2311},{"date":"2026-04-26T07:21:40Z","avgVariable":0.0656,"avgFixed":0.0661,"lowestVariable":0.0424,"lowestFixed":0.0559,"bankCount":62,"rateCount":2311},{"date":"2026-04-26T12:53:11Z","avgVariable":0.0656,"avgFixed":0.0661,"lowestVariable":0.0424,"lowestFixed":0.0559,"bankCount":62,"rateCount":2311},{"date":"2026-04-26T18:43:24Z","avgVariable":0.0656,"avgFixed":0.0661,"lowestVariable":0.0424,"lowestFixed":0.0559,"bankCount":62,"rateCount":2341},{"date":"2026-04-27T02:08:36Z","avgVariable":0.0656,"avgFixed":0.0661,"lowestVariable":0.0424,"lowestFixed":0.0559,"bankCount":61,"rateCount":2273},{"date":"2026-04-27T08:12:38Z","avgVariable":0.0656,"avgFixed":0.0661,"lowestVariable":0.0424,"lowestFixed":0.0559,"bankCount":62,"rateCount":2311},{"date":"2026-04-27T13:25:59Z","avgVariable":0.0656,"avgFixed":0.0661,"lowestVariable":0.0424,"lowestFixed":0.0559,"bankCount":62,"rateCount":2311},{"date":"2026-04-27T19:09:47Z","avgVariable":0.0656,"avgFixed":0.0661,"lowestVariable":0.0424,"lowestFixed":0.0559,"bankCount":62,"rateCount":2311},{"date":"2026-04-28T02:15:11Z","avgVariable":0.0657,"avgFixed":0.0661,"lowestVariable":0.0424,"lowestFixed":0.0559,"bankCount":62,"rateCount":2305},{"date":"2026-04-28T08:14:21Z","avgVariable":0.0656,"avgFixed":0.066,"lowestVariable":0.0424,"lowestFixed":0.0559,"bankCount":61,"rateCount":2194},{"date":"2026-04-28T19:26:26Z","avgVariable":0.0656,"avgFixed":0.0658,"lowestVariable":0.0424,"lowestFixed":0.0559,"bankCount":57,"rateCount":2114},{"date":"2026-04-29T02:16:07Z","avgVariable":0.0656,"avgFixed":0.0661,"lowestVariable":0.0424,"lowestFixed":0.0571,"bankCount":60,"rateCount":2174},{"date":"2026-04-29T08:07:04Z","avgVariable":0.0656,"avgFixed":0.0661,"lowestVariable":0.0424,"lowestFixed":0.0571,"bankCount":60,"rateCount":2174},{"date":"2026-04-29T13:31:44Z","avgVariable":0.0656,"avgFixed":0.0661,"lowestVariable":0.0424,"lowestFixed":0.0571,"bankCount":60,"rateCount":2174},{"date":"2026-04-29T19:16:21Z","avgVariable":0.0656,"avgFixed":0.0661,"lowestVariable":0.0424,"lowestFixed":0.0571,"bankCount":60,"rateCount":2174},{"date":"2026-04-30T03:14:26Z","avgVariable":0.0658,"avgFixed":0.066,"lowestVariable":0.0424,"lowestFixed":0.0571,"bankCount":59,"rateCount":2048},{"date":"2026-05-01T13:05:53Z","avgVariable":0.0645,"avgFixed":0.0645,"lowestVariable":0.0554,"lowestFixed":0.0584,"bankCount":17,"rateCount":723},{"date":"2026-05-01T19:03:36Z","avgVariable":0.0645,"avgFixed":0.0645,"lowestVariable":0.0554,"lowestFixed":0.0584,"bankCount":17,"rateCount":723},{"date":"2026-05-02T02:07:30Z","avgVariable":0.0645,"avgFixed":0.0645,"lowestVariable":0.0554,"lowestFixed":0.0584,"bankCount":17,"rateCount":723},{"date":"2026-05-02T07:24:45Z","avgVariable":0.0645,"avgFixed":0.0645,"lowestVariable":0.0554,"lowestFixed":0.0584,"bankCount":17,"rateCount":723}],"topMovers":[{"bankName":"Gateway Bank","productName":"Low Rate Essentials Int Only","rateType":"VARIABLE","currentRate":0.0664,"pastRate":0.0916,"changeBps":-252,"snapshots":199},{"bankName":"BNK Bank (Goldfields Money/BCHL)","productName":"Gold Prime Residential Special Home Loans","rateType":"VARIABLE","currentRate":0.059,"pastRate":0.0814,"changeBps":-224,"snapshots":12},{"bankName":"Bank of China","productName":"Discount Investment Home Loan (With Principal and Interest Repayment)","rateType":"VARIABLE","currentRate":0.0588,"pastRate":0.0775,"changeBps":-187,"snapshots":84},{"bankName":"Bank of China","productName":"Discount Plus Investment Home Loan (with Principal and Interest Repayment)","rateType":"VARIABLE","currentRate":0.0588,"pastRate":0.0775,"changeBps":-187,"snapshots":84},{"bankName":"Bank of China","productName":"Discount Investment Home Loan (with Interest Only Repayment)","rateType":"VARIABLE","currentRate":0.0588,"pastRate":0.0775,"changeBps":-187,"snapshots":84},{"bankName":"Bank of China","productName":"Discount Plus Investment Home Loan (with Interest Only Repayment)","rateType":"VARIABLE","currentRate":0.0588,"pastRate":0.0775,"changeBps":-187,"snapshots":84},{"bankName":"BNK Bank (Goldfields Money/BCHL)","productName":"Gold Prime Residential Special Home Loans","rateType":"VARIABLE","currentRate":0.0625,"pastRate":0.0807,"changeBps":-182,"snapshots":9},{"bankName":"Beyond Bank Australia","productName":"Invest Total Home Loan Package","rateType":"VARIABLE","currentRate":0.0619,"pastRate":0.08,"changeBps":-181,"snapshots":129},{"bankName":"Beyond Bank Australia","productName":"Invest Total Home Loan Package","rateType":"VARIABLE","currentRate":0.0599,"pastRate":0.0775,"changeBps":-176,"snapshots":258},{"bankName":"Bank of China","productName":"Discount Home Loan (With Principal and Interest Repayment)","rateType":"VARIABLE","currentRate":0.0568,"pastRate":0.0744,"changeBps":-176,"snapshots":84}],"trendBuckets":[{"bucket":"Falling fast","count":8384},{"bucket":"Falling","count":625},{"bucket":"Flat","count":64500},{"bucket":"Rising","count":12034},{"bucket":"Rising fast","count":15584},{"bucket":"No history","count":1438}],"rateDistribution":[{"bucket":"5.5%","variable":1,"fixed":0},{"bucket":"5.6%","variable":8,"fixed":0},{"bucket":"5.7%","variable":21,"fixed":0},{"bucket":"5.8%","variable":22,"fixed":8},{"bucket":"5.9%","variable":23,"fixed":10},{"bucket":"6.0%","variable":27,"fixed":60},{"bucket":"6.1%","variable":51,"fixed":72},{"bucket":"6.2%","variable":41,"fixed":60},{"bucket":"6.3%","variable":13,"fixed":70},{"bucket":"6.4%","variable":2,"fixed":39},{"bucket":"6.5%","variable":4,"fixed":34},{"bucket":"6.6%","variable":0,"fixed":20},{"bucket":"6.7%","variable":1,"fixed":28},{"bucket":"6.8%","variable":4,"fixed":10},{"bucket":"6.9%","variable":0,"fixed":8},{"bucket":"7.0%","variable":1,"fixed":6},{"bucket":"7.1%","variable":3,"fixed":2},{"bucket":"7.2%","variable":3,"fixed":5},{"bucket":"7.3%","variable":0,"fixed":1},{"bucket":"7.4%","variable":1,"fixed":0},{"bucket":"7.5%","variable":1,"fixed":0},{"bucket":"7.6%","variable":3,"fixed":0},{"bucket":"7.7%","variable":4,"fixed":1},{"bucket":"7.8%","variable":2,"fixed":0},{"bucket":"7.9%","variable":2,"fixed":0},{"bucket":"8.0%","variable":2,"fixed":0},{"bucket":"8.1%","variable":7,"fixed":0},{"bucket":"8.2%","variable":3,"fixed":0},{"bucket":"8.4%","variable":4,"fixed":0},{"bucket":"8.5%","variable":2,"fixed":0},{"bucket":"8.6%","variable":3,"fixed":0},{"bucket":"9.0%","variable":4,"fixed":0},{"bucket":"9.1%","variable":1,"fixed":0},{"bucket":"9.2%","variable":1,"fixed":0},{"bucket":"9.3%","variable":2,"fixed":8},{"bucket":"9.4%","variable":1,"fixed":12},{"bucket":"10.4%","variable":1,"fixed":0}],"featurePrevalence":[{"feature":"guarantor","label":"Guarantor option","count":85,"pct":11.8},{"feature":"package","label":"Package deal","count":49,"pct":6.8},{"feature":"first_home_buyer","label":"First home buyer","count":26,"pct":3.6},{"feature":"offset","label":"Offset account","count":447,"pct":61.8},{"feature":"redraw","label":"Redraw facility","count":677,"pct":93.6},{"feature":"extra_repayments","label":"Extra repayments","count":570,"pct":78.8},{"feature":"cashback","label":"Cashback offer","count":56,"pct":7.7}],"rateByLvr":[{"band":"≤60% LVR","avgVariable":0.0601,"avgFixed":0.0617,"count":91},{"band":"60–80% LVR","avgVariable":0.0625,"avgFixed":0.0638,"count":99},{"band":"80–95% LVR","avgVariable":0.0627,"avgFixed":0.063,"count":189}],"variableVsFixed":[{"date":"2026-04-19T05:18:36Z","variablePct":42.9,"variableCount":1039,"fixedCount":1384},{"date":"2026-04-19T12:46:24Z","variablePct":42.8,"variableCount":1034,"fixedCount":1384},{"date":"2026-04-19T18:40:37Z","variablePct":42.9,"variableCount":1041,"fixedCount":1384},{"date":"2026-04-20T02:04:37Z","variablePct":42.5,"variableCount":1025,"fixedCount":1384},{"date":"2026-04-20T07:57:51Z","variablePct":42.5,"variableCount":1023,"fixedCount":1384},{"date":"2026-04-20T13:16:56Z","variablePct":42.5,"variableCount":1025,"fixedCount":1384},{"date":"2026-04-20T18:58:29Z","variablePct":42.5,"variableCount":1023,"fixedCount":1384},{"date":"2026-04-21T02:00:04Z","variablePct":42.6,"variableCount":1027,"fixedCount":1384},{"date":"2026-04-21T07:27:52Z","variablePct":42.8,"variableCount":1035,"fixedCount":1384},{"date":"2026-04-21T13:10:25Z","variablePct":41.9,"variableCount":955,"fixedCount":1324},{"date":"2026-04-21T19:04:48Z","variablePct":41.9,"variableCount":1085,"fixedCount":1504},{"date":"2026-04-22T01:58:36Z","variablePct":42.8,"variableCount":1035,"fixedCount":1384},{"date":"2026-04-22T07:25:40Z","variablePct":42.8,"variableCount":1035,"fixedCount":1384},{"date":"2026-04-22T13:14:14Z","variablePct":42.7,"variableCount":1033,"fixedCount":1384},{"date":"2026-04-22T19:06:17Z","variablePct":40.2,"variableCount":799,"fixedCount":1190},{"date":"2026-04-23T02:02:58Z","variablePct":42.7,"variableCount":1031,"fixedCount":1384},{"date":"2026-04-23T07:28:18Z","variablePct":42.7,"variableCount":1030,"fixedCount":1384},{"date":"2026-04-23T13:12:16Z","variablePct":41.4,"variableCount":955,"fixedCount":1354},{"date":"2026-04-23T19:02:24Z","variablePct":41.3,"variableCount":969,"fixedCount":1380},{"date":"2026-04-24T02:02:51Z","variablePct":41.4,"variableCount":955,"fixedCount":1352},{"date":"2026-04-24T07:54:16Z","variablePct":41.5,"variableCount":959,"fixedCount":1352},{"date":"2026-04-24T13:09:03Z","variablePct":41.5,"variableCount":959,"fixedCount":1352},{"date":"2026-04-24T18:42:14Z","variablePct":41.3,"variableCount":965,"fixedCount":1372},{"date":"2026-04-25T01:52:30Z","variablePct":41.5,"variableCount":959,"fixedCount":1352},{"date":"2026-04-25T07:07:28Z","variablePct":41.5,"variableCount":959,"fixedCount":1352},{"date":"2026-04-25T12:47:59Z","variablePct":41.5,"variableCount":959,"fixedCount":1352},{"date":"2026-04-25T18:42:02Z","variablePct":41.5,"variableCount":958,"fixedCount":1352},{"date":"2026-04-26T02:06:23Z","variablePct":41.5,"variableCount":959,"fixedCount":1352},{"date":"2026-04-26T07:21:40Z","variablePct":41.5,"variableCount":959,"fixedCount":1352},{"date":"2026-04-26T12:53:11Z","variablePct":41.5,"variableCount":959,"fixedCount":1352},{"date":"2026-04-26T18:43:24Z","variablePct":41.4,"variableCount":969,"fixedCount":1372},{"date":"2026-04-27T02:08:36Z","variablePct":41.4,"variableCount":941,"fixedCount":1332},{"date":"2026-04-27T08:12:38Z","variablePct":41.5,"variableCount":959,"fixedCount":1352},{"date":"2026-04-27T13:25:59Z","variablePct":41.5,"variableCount":959,"fixedCount":1352},{"date":"2026-04-27T19:09:47Z","variablePct":41.5,"variableCount":959,"fixedCount":1352},{"date":"2026-04-28T02:15:11Z","variablePct":41.4,"variableCount":954,"fixedCount":1351},{"date":"2026-04-28T08:14:21Z","variablePct":41.3,"variableCount":907,"fixedCount":1287},{"date":"2026-04-28T19:26:26Z","variablePct":42.9,"variableCount":907,"fixedCount":1207},{"date":"2026-04-29T02:16:07Z","variablePct":41.6,"variableCount":904,"fixedCount":1270},{"date":"2026-04-29T08:07:04Z","variablePct":41.6,"variableCount":904,"fixedCount":1270},{"date":"2026-04-29T13:31:44Z","variablePct":41.6,"variableCount":904,"fixedCount":1270},{"date":"2026-04-29T19:16:21Z","variablePct":41.6,"variableCount":904,"fixedCount":1270},{"date":"2026-04-30T03:14:26Z","variablePct":42.4,"variableCount":868,"fixedCount":1180},{"date":"2026-05-01T13:05:53Z","variablePct":37.2,"variableCount":269,"fixedCount":454},{"date":"2026-05-01T19:03:36Z","variablePct":37.2,"variableCount":269,"fixedCount":454},{"date":"2026-05-02T02:07:30Z","variablePct":37.2,"variableCount":269,"fixedCount":454},{"date":"2026-05-02T07:24:45Z","variablePct":37.2,"variableCount":269,"fixedCount":454}],"cashbackBanks":[{"bankName":"Greater Bank","productName":"Discounted Great Rate Home Loan - Variable Interest Only Investment","detail":"Switching to Greater Bank could score you up to $2,500 cashback. Applicable for eligible owner occupied and investment home loans. $2,000 cashback for loans ≥$250,000 with LVR of less than or equal to 80%, or $2,500 cashback for loans ≥$500,000 with LVR of less than or equal to 80%. Only one (1) Cashback Payment per eligible loan, and for first eligible loan only. Not available in conjunction with any other promotional payment. Offer may be varied or withdrawn at any time. See the full Cashback Offer Terms and Conditions. Terms, conditions, fees, charges and credit criteria apply."}]}